<?xml version="1.0" encoding="utf-8"?>
          <actions>
          <action>
            <action_id>create_Content_Container_Template_2324837525</action_id>
            <action_type>create_asset</action_type>
            <type_code>Content_Container_Template</type_code>
            <link_type>1</link_type>
            <parentid>1</parentid>
            <value></value>
            <is_dependant>0</is_dependant>
            <is_exclusive>0</is_exclusive>
          </action>
          <action>
            <action_id>set_Content_Container_Template_2324837525_name</action_id>
            <action_type>set_attribute_value</action_type>
            <asset>[[output://create_Content_Container_Template_2324837525.assetid]]</asset>
            <attribute>name</attribute>
            <value><![CDATA[Promo Panel]]></value>
          </action>

          <action>
            <action_id>set_Content_Container_Template_2324837525_edit_interface_in_admin</action_id>
            <action_type>set_attribute_value</action_type>
            <asset>[[output://create_Content_Container_Template_2324837525.assetid]]</asset>
            <attribute>edit_interface_in_admin</attribute>
            <value><![CDATA[1]]></value>
          </action>

          <action>
            <action_id>set_Content_Container_Template_2324837525_icon_color</action_id>
            <action_type>set_attribute_value</action_type>
            <asset>[[output://create_Content_Container_Template_2324837525.assetid]]</asset>
            <attribute>icon_color</attribute>
            <value><![CDATA[blue]]></value>
          </action>
          
          <action>
          <action_id>create_Metadata_Schema_498066716</action_id>
          <action_type>create_asset</action_type>
          <type_code>Metadata_Schema</type_code>
          <link_type>1</link_type>
          <parentid>[[output://create_Content_Container_Template_2324837525.assetid]]</parentid>
          <value></value>
          <is_dependant>0</is_dependant>
          <is_exclusive>0</is_exclusive>
          </action>
          <action>
            <action_id>set_Metadata_Schema_498066716_name</action_id>
            <action_type>set_attribute_value</action_type>
            <asset>[[output://create_Metadata_Schema_498066716.assetid]]</asset>
            <attribute>name</attribute>
            <value><![CDATA[Promo Panel]]></value>
          </action>
          <action>
              <action_id>set_permission_498066716_read_5</action_id>
              <action_type>set_permission</action_type>
              <asset>[[output://create_Metadata_Schema_498066716.assetid]]</asset>
              <permission>1</permission>
              <granted>1</granted>
              <userid>[[system://public_user]]</userid>
          </action>
          
          <action>
            <action_id>create_Metadata_Section_752087999</action_id>
            <action_type>create_asset</action_type>
            <type_code>Metadata_Section</type_code>
            <link_type>2</link_type>
            <parentid>[[output://create_Metadata_Schema_498066716.assetid]]</parentid>
            <value></value>
            <is_dependant>1</is_dependant>
            <is_exclusive>0</is_exclusive>
          </action>
          <action>
            <action_id>add_Metadata_Section_752087999_path</action_id>
            <action_type>add_web_path</action_type>
            <asset>[[output://create_Metadata_Section_752087999.assetid]]</asset>
            <parent_asset>[[output://create_Metadata_Schema_498066716.assetid]]</parent_asset>
            <path>settings</path>
          </action>
          <action>
            <action_id>set_Metadata_Section_752087999_name</action_id>
            <action_type>set_attribute_value</action_type>
            <asset>[[output://create_Metadata_Section_752087999.assetid]]</asset>
            <attribute>name</attribute>
            <value><![CDATA[Settings]]></value>
          </action>
          <action>
              <action_id>set_permission_752087999_read_5</action_id>
              <action_type>set_permission</action_type>
              <asset>[[output://create_Metadata_Section_752087999.assetid]]</asset>
              <permission>1</permission>
              <granted>1</granted>
              <userid>[[system://public_user]]</userid>
          </action>           
          
              <action>
                  <action_id>create_metadata_field_select_9112150626</action_id>
                  <action_type>create_asset</action_type>
                  <type_code>metadata_field_select</type_code>
                  <link_type>2</link_type>
                  <parentid>[[output://create_Metadata_Section_752087999.assetid]]</parentid>
                  <value></value>
                  <is_dependant>1</is_dependant>
                  <is_exclusive>0</is_exclusive>
              </action> 
              <action>
                  <action_id>set_metadata_field_select_9112150626_name</action_id>
                  <action_type>set_attribute_value</action_type>
                  <asset>[[output://create_metadata_field_select_9112150626.assetid]]</asset>
                  <attribute>name</attribute>
                  <value><![CDATA[body_background]]></value>
              </action>
              <action>
                  <action_id>set_metadata_field_select_9112150626_friendly_name</action_id>
                  <action_type>set_attribute_value</action_type>
                  <asset>[[output://create_metadata_field_select_9112150626.assetid]]</asset>
                  <attribute>friendly_name</attribute>
                  <value><![CDATA[Background colour]]></value>
              </action>
              <action>
                  <action_id>set_metadata_field_select_9112150626_default</action_id>
                  <action_type>set_attribute_value</action_type>
                  <asset>[[output://create_metadata_field_select_9112150626.assetid]]</asset>
                  <attribute>default</attribute>
                  <value><![CDATA[qld__body--dark-alt]]></value>
              </action>
              <action>
                  <action_id>set_metadata_field_select_9112150626_description</action_id>
                  <action_type>set_attribute_value</action_type>
                  <asset>[[output://create_metadata_field_select_9112150626.assetid]]</asset>
                  <attribute>description</attribute>
                  <value><![CDATA[]]></value>
              </action>
              <action>
                  <action_id>set_metadata_field_select_9112150626_editable</action_id>
                  <action_type>set_attribute_value</action_type>
                  <asset>[[output://create_metadata_field_select_9112150626.assetid]]</asset>
                  <attribute>editable</attribute>
                  <value><![CDATA[1]]></value>
              </action>
              <action>
                  <action_id>set_metadata_field_select_9112150626_editable</action_id>
                  <action_type>set_attribute_value</action_type>
                  <asset>[[output://create_metadata_field_select_9112150626.assetid]]</asset>
                  <attribute>editable</attribute>
                  <value><![CDATA[1]]></value>
              </action>
              <action>
                  <action_id>set_metadata_field_select_9112150626_required</action_id>
                  <action_type>set_attribute_value</action_type>
                  <asset>[[output://create_metadata_field_select_9112150626.assetid]]</asset>
                  <attribute>required</attribute>
                  <value><![CDATA[0]]></value>
              </action>
              <action>
                  <action_id>set_permission_9112150626_read_5</action_id>
                  <action_type>set_permission</action_type>
                  <asset>[[output://create_metadata_field_select_9112150626.assetid]]</asset>
                  <permission>1</permission>
                  <granted>1</granted>
                  <userid>[[system://public_user]]</userid>
              </action>
              
                  <action>
                      <action_id>set_metadata_field_select_9112150626_select_options</action_id>
                      <action_type>set_attribute_value</action_type>
                      <asset>[[output://create_metadata_field_select_9112150626.assetid]]</asset>
                      <attribute>select_options</attribute>
                      <value><![CDATA[array ('' => 'White','qld__body--light' => 'Light','qld__body--alt' => 'Alternate','qld__body--dark' => 'Dark','qld__body--dark-alt' => 'Alternate Dark',);]]></value>
                  </action>
                  <action>
                      <action_id>set_{f.type}_9112150626_edit_params</action_id>
                      <action_type>set_attribute_value</action_type>
                      <asset>[[output://create_metadata_field_select_9112150626.assetid]]</asset>
                      <attribute>edit_params</attribute>
                      <value><![CDATA[array (
                      'style' => 'list',
                      'type' => 'table',
                      'height' => '',
                      'columns' => '1',
                      'empty_text' => '',
                      'extras' => '',
                      );]]></value>
                  </action>  
                  
              <action>
                  <action_id>create_metadata_field_select_9799355272</action_id>
                  <action_type>create_asset</action_type>
                  <type_code>metadata_field_select</type_code>
                  <link_type>2</link_type>
                  <parentid>[[output://create_Metadata_Section_752087999.assetid]]</parentid>
                  <value></value>
                  <is_dependant>1</is_dependant>
                  <is_exclusive>0</is_exclusive>
              </action> 
              <action>
                  <action_id>set_metadata_field_select_9799355272_name</action_id>
                  <action_type>set_attribute_value</action_type>
                  <asset>[[output://create_metadata_field_select_9799355272.assetid]]</asset>
                  <attribute>name</attribute>
                  <value><![CDATA[type]]></value>
              </action>
              <action>
                  <action_id>set_metadata_field_select_9799355272_friendly_name</action_id>
                  <action_type>set_attribute_value</action_type>
                  <asset>[[output://create_metadata_field_select_9799355272.assetid]]</asset>
                  <attribute>friendly_name</attribute>
                  <value><![CDATA[Variant]]></value>
              </action>
              <action>
                  <action_id>set_metadata_field_select_9799355272_default</action_id>
                  <action_type>set_attribute_value</action_type>
                  <asset>[[output://create_metadata_field_select_9799355272.assetid]]</asset>
                  <attribute>default</attribute>
                  <value><![CDATA[]]></value>
              </action>
              <action>
                  <action_id>set_metadata_field_select_9799355272_description</action_id>
                  <action_type>set_attribute_value</action_type>
                  <asset>[[output://create_metadata_field_select_9799355272.assetid]]</asset>
                  <attribute>description</attribute>
                  <value><![CDATA[]]></value>
              </action>
              <action>
                  <action_id>set_metadata_field_select_9799355272_editable</action_id>
                  <action_type>set_attribute_value</action_type>
                  <asset>[[output://create_metadata_field_select_9799355272.assetid]]</asset>
                  <attribute>editable</attribute>
                  <value><![CDATA[1]]></value>
              </action>
              <action>
                  <action_id>set_metadata_field_select_9799355272_editable</action_id>
                  <action_type>set_attribute_value</action_type>
                  <asset>[[output://create_metadata_field_select_9799355272.assetid]]</asset>
                  <attribute>editable</attribute>
                  <value><![CDATA[1]]></value>
              </action>
              <action>
                  <action_id>set_metadata_field_select_9799355272_required</action_id>
                  <action_type>set_attribute_value</action_type>
                  <asset>[[output://create_metadata_field_select_9799355272.assetid]]</asset>
                  <attribute>required</attribute>
                  <value><![CDATA[0]]></value>
              </action>
              <action>
                  <action_id>set_permission_9799355272_read_5</action_id>
                  <action_type>set_permission</action_type>
                  <asset>[[output://create_metadata_field_select_9799355272.assetid]]</asset>
                  <permission>1</permission>
                  <granted>1</granted>
                  <userid>[[system://public_user]]</userid>
              </action>
              
                  <action>
                      <action_id>set_metadata_field_select_9799355272_select_options</action_id>
                      <action_type>set_attribute_value</action_type>
                      <asset>[[output://create_metadata_field_select_9799355272.assetid]]</asset>
                      <attribute>select_options</attribute>
                      <value><![CDATA[array ('' => 'Large image','qld__body--large-text' => 'Large text','qld__body--contained' => 'Contained','qld__body--full-image' => 'Full image',);]]></value>
                  </action>
                  <action>
                      <action_id>set_{f.type}_9799355272_edit_params</action_id>
                      <action_type>set_attribute_value</action_type>
                      <asset>[[output://create_metadata_field_select_9799355272.assetid]]</asset>
                      <attribute>edit_params</attribute>
                      <value><![CDATA[array (
                      'style' => 'list',
                      'type' => 'table',
                      'height' => '',
                      'columns' => '1',
                      'empty_text' => '',
                      'extras' => '',
                      );]]></value>
                  </action>  
                  
              <action>
                  <action_id>create_metadata_field_related_asset_9415798050</action_id>
                  <action_type>create_asset</action_type>
                  <type_code>metadata_field_related_asset</type_code>
                  <link_type>2</link_type>
                  <parentid>[[output://create_Metadata_Section_752087999.assetid]]</parentid>
                  <value></value>
                  <is_dependant>1</is_dependant>
                  <is_exclusive>0</is_exclusive>
              </action> 
              <action>
                  <action_id>set_metadata_field_related_asset_9415798050_name</action_id>
                  <action_type>set_attribute_value</action_type>
                  <asset>[[output://create_metadata_field_related_asset_9415798050.assetid]]</asset>
                  <attribute>name</attribute>
                  <value><![CDATA[promo_image]]></value>
              </action>
              <action>
                  <action_id>set_metadata_field_related_asset_9415798050_friendly_name</action_id>
                  <action_type>set_attribute_value</action_type>
                  <asset>[[output://create_metadata_field_related_asset_9415798050.assetid]]</asset>
                  <attribute>friendly_name</attribute>
                  <value><![CDATA[Image]]></value>
              </action>
              <action>
                  <action_id>set_metadata_field_related_asset_9415798050_default</action_id>
                  <action_type>set_attribute_value</action_type>
                  <asset>[[output://create_metadata_field_related_asset_9415798050.assetid]]</asset>
                  <attribute>default</attribute>
                  <value><![CDATA[https://www.health.qld.gov.au/__data/assets/image/0033/1168368/varieties/800-lg.png]]></value>
              </action>
              <action>
                  <action_id>set_metadata_field_related_asset_9415798050_description</action_id>
                  <action_type>set_attribute_value</action_type>
                  <asset>[[output://create_metadata_field_related_asset_9415798050.assetid]]</asset>
                  <attribute>description</attribute>
                  <value><![CDATA[]]></value>
              </action>
              <action>
                  <action_id>set_metadata_field_related_asset_9415798050_editable</action_id>
                  <action_type>set_attribute_value</action_type>
                  <asset>[[output://create_metadata_field_related_asset_9415798050.assetid]]</asset>
                  <attribute>editable</attribute>
                  <value><![CDATA[1]]></value>
              </action>
              <action>
                  <action_id>set_metadata_field_related_asset_9415798050_editable</action_id>
                  <action_type>set_attribute_value</action_type>
                  <asset>[[output://create_metadata_field_related_asset_9415798050.assetid]]</asset>
                  <attribute>editable</attribute>
                  <value><![CDATA[1]]></value>
              </action>
              <action>
                  <action_id>set_metadata_field_related_asset_9415798050_required</action_id>
                  <action_type>set_attribute_value</action_type>
                  <asset>[[output://create_metadata_field_related_asset_9415798050.assetid]]</asset>
                  <attribute>required</attribute>
                  <value><![CDATA[0]]></value>
              </action>
              <action>
                  <action_id>set_permission_9415798050_read_5</action_id>
                  <action_type>set_permission</action_type>
                  <asset>[[output://create_metadata_field_related_asset_9415798050.assetid]]</asset>
                  <permission>1</permission>
                  <granted>1</granted>
                  <userid>[[system://public_user]]</userid>
              </action>
              
              <action>
                  <action_id>create_metadata_field_select_1330710844</action_id>
                  <action_type>create_asset</action_type>
                  <type_code>metadata_field_select</type_code>
                  <link_type>2</link_type>
                  <parentid>[[output://create_Metadata_Section_752087999.assetid]]</parentid>
                  <value></value>
                  <is_dependant>1</is_dependant>
                  <is_exclusive>0</is_exclusive>
              </action> 
              <action>
                  <action_id>set_metadata_field_select_1330710844_name</action_id>
                  <action_type>set_attribute_value</action_type>
                  <asset>[[output://create_metadata_field_select_1330710844.assetid]]</asset>
                  <attribute>name</attribute>
                  <value><![CDATA[image_alignment]]></value>
              </action>
              <action>
                  <action_id>set_metadata_field_select_1330710844_friendly_name</action_id>
                  <action_type>set_attribute_value</action_type>
                  <asset>[[output://create_metadata_field_select_1330710844.assetid]]</asset>
                  <attribute>friendly_name</attribute>
                  <value><![CDATA[Image alignment]]></value>
              </action>
              <action>
                  <action_id>set_metadata_field_select_1330710844_default</action_id>
                  <action_type>set_attribute_value</action_type>
                  <asset>[[output://create_metadata_field_select_1330710844.assetid]]</asset>
                  <attribute>default</attribute>
                  <value><![CDATA[qld__promo-panel--image-right]]></value>
              </action>
              <action>
                  <action_id>set_metadata_field_select_1330710844_description</action_id>
                  <action_type>set_attribute_value</action_type>
                  <asset>[[output://create_metadata_field_select_1330710844.assetid]]</asset>
                  <attribute>description</attribute>
                  <value><![CDATA[]]></value>
              </action>
              <action>
                  <action_id>set_metadata_field_select_1330710844_editable</action_id>
                  <action_type>set_attribute_value</action_type>
                  <asset>[[output://create_metadata_field_select_1330710844.assetid]]</asset>
                  <attribute>editable</attribute>
                  <value><![CDATA[1]]></value>
              </action>
              <action>
                  <action_id>set_metadata_field_select_1330710844_editable</action_id>
                  <action_type>set_attribute_value</action_type>
                  <asset>[[output://create_metadata_field_select_1330710844.assetid]]</asset>
                  <attribute>editable</attribute>
                  <value><![CDATA[1]]></value>
              </action>
              <action>
                  <action_id>set_metadata_field_select_1330710844_required</action_id>
                  <action_type>set_attribute_value</action_type>
                  <asset>[[output://create_metadata_field_select_1330710844.assetid]]</asset>
                  <attribute>required</attribute>
                  <value><![CDATA[0]]></value>
              </action>
              <action>
                  <action_id>set_permission_1330710844_read_5</action_id>
                  <action_type>set_permission</action_type>
                  <asset>[[output://create_metadata_field_select_1330710844.assetid]]</asset>
                  <permission>1</permission>
                  <granted>1</granted>
                  <userid>[[system://public_user]]</userid>
              </action>
              
                  <action>
                      <action_id>set_metadata_field_select_1330710844_select_options</action_id>
                      <action_type>set_attribute_value</action_type>
                      <asset>[[output://create_metadata_field_select_1330710844.assetid]]</asset>
                      <attribute>select_options</attribute>
                      <value><![CDATA[array ('qld__promo-panel--image-left' => 'Left','qld__promo-panel--image-right' => 'Right',);]]></value>
                  </action>
                  <action>
                      <action_id>set_{f.type}_1330710844_edit_params</action_id>
                      <action_type>set_attribute_value</action_type>
                      <asset>[[output://create_metadata_field_select_1330710844.assetid]]</asset>
                      <attribute>edit_params</attribute>
                      <value><![CDATA[array (
                      'style' => 'list',
                      'type' => 'table',
                      'height' => '',
                      'columns' => '1',
                      'empty_text' => '',
                      'extras' => '',
                      );]]></value>
                  </action>  
                  
              <action>
                  <action_id>create_metadata_field_text_2951890940</action_id>
                  <action_type>create_asset</action_type>
                  <type_code>metadata_field_text</type_code>
                  <link_type>2</link_type>
                  <parentid>[[output://create_Metadata_Section_752087999.assetid]]</parentid>
                  <value></value>
                  <is_dependant>1</is_dependant>
                  <is_exclusive>0</is_exclusive>
              </action> 
              <action>
                  <action_id>set_metadata_field_text_2951890940_name</action_id>
                  <action_type>set_attribute_value</action_type>
                  <asset>[[output://create_metadata_field_text_2951890940.assetid]]</asset>
                  <attribute>name</attribute>
                  <value><![CDATA[icon]]></value>
              </action>
              <action>
                  <action_id>set_metadata_field_text_2951890940_friendly_name</action_id>
                  <action_type>set_attribute_value</action_type>
                  <asset>[[output://create_metadata_field_text_2951890940.assetid]]</asset>
                  <attribute>friendly_name</attribute>
                  <value><![CDATA[Icon]]></value>
              </action>
              <action>
                  <action_id>set_metadata_field_text_2951890940_default</action_id>
                  <action_type>set_attribute_value</action_type>
                  <asset>[[output://create_metadata_field_text_2951890940.assetid]]</asset>
                  <attribute>default</attribute>
                  <value><![CDATA[fa fa-wifi]]></value>
              </action>
              <action>
                  <action_id>set_metadata_field_text_2951890940_description</action_id>
                  <action_type>set_attribute_value</action_type>
                  <asset>[[output://create_metadata_field_text_2951890940.assetid]]</asset>
                  <attribute>description</attribute>
                  <value><![CDATA[]]></value>
              </action>
              <action>
                  <action_id>set_metadata_field_text_2951890940_editable</action_id>
                  <action_type>set_attribute_value</action_type>
                  <asset>[[output://create_metadata_field_text_2951890940.assetid]]</asset>
                  <attribute>editable</attribute>
                  <value><![CDATA[1]]></value>
              </action>
              <action>
                  <action_id>set_metadata_field_text_2951890940_editable</action_id>
                  <action_type>set_attribute_value</action_type>
                  <asset>[[output://create_metadata_field_text_2951890940.assetid]]</asset>
                  <attribute>editable</attribute>
                  <value><![CDATA[1]]></value>
              </action>
              <action>
                  <action_id>set_metadata_field_text_2951890940_required</action_id>
                  <action_type>set_attribute_value</action_type>
                  <asset>[[output://create_metadata_field_text_2951890940.assetid]]</asset>
                  <attribute>required</attribute>
                  <value><![CDATA[0]]></value>
              </action>
              <action>
                  <action_id>set_permission_2951890940_read_5</action_id>
                  <action_type>set_permission</action_type>
                  <asset>[[output://create_metadata_field_text_2951890940.assetid]]</asset>
                  <permission>1</permission>
                  <granted>1</granted>
                  <userid>[[system://public_user]]</userid>
              </action>
              
              <action>
                  <action_id>create_metadata_field_text_1573062249</action_id>
                  <action_type>create_asset</action_type>
                  <type_code>metadata_field_text</type_code>
                  <link_type>2</link_type>
                  <parentid>[[output://create_Metadata_Section_752087999.assetid]]</parentid>
                  <value></value>
                  <is_dependant>1</is_dependant>
                  <is_exclusive>0</is_exclusive>
              </action> 
              <action>
                  <action_id>set_metadata_field_text_1573062249_name</action_id>
                  <action_type>set_attribute_value</action_type>
                  <asset>[[output://create_metadata_field_text_1573062249.assetid]]</asset>
                  <attribute>name</attribute>
                  <value><![CDATA[title]]></value>
              </action>
              <action>
                  <action_id>set_metadata_field_text_1573062249_friendly_name</action_id>
                  <action_type>set_attribute_value</action_type>
                  <asset>[[output://create_metadata_field_text_1573062249.assetid]]</asset>
                  <attribute>friendly_name</attribute>
                  <value><![CDATA[Title]]></value>
              </action>
              <action>
                  <action_id>set_metadata_field_text_1573062249_default</action_id>
                  <action_type>set_attribute_value</action_type>
                  <asset>[[output://create_metadata_field_text_1573062249.assetid]]</asset>
                  <attribute>default</attribute>
                  <value><![CDATA[Title goes here and has a maximum of 64 character limit]]></value>
              </action>
              <action>
                  <action_id>set_metadata_field_text_1573062249_description</action_id>
                  <action_type>set_attribute_value</action_type>
                  <asset>[[output://create_metadata_field_text_1573062249.assetid]]</asset>
                  <attribute>description</attribute>
                  <value><![CDATA[]]></value>
              </action>
              <action>
                  <action_id>set_metadata_field_text_1573062249_editable</action_id>
                  <action_type>set_attribute_value</action_type>
                  <asset>[[output://create_metadata_field_text_1573062249.assetid]]</asset>
                  <attribute>editable</attribute>
                  <value><![CDATA[1]]></value>
              </action>
              <action>
                  <action_id>set_metadata_field_text_1573062249_editable</action_id>
                  <action_type>set_attribute_value</action_type>
                  <asset>[[output://create_metadata_field_text_1573062249.assetid]]</asset>
                  <attribute>editable</attribute>
                  <value><![CDATA[1]]></value>
              </action>
              <action>
                  <action_id>set_metadata_field_text_1573062249_required</action_id>
                  <action_type>set_attribute_value</action_type>
                  <asset>[[output://create_metadata_field_text_1573062249.assetid]]</asset>
                  <attribute>required</attribute>
                  <value><![CDATA[0]]></value>
              </action>
              <action>
                  <action_id>set_permission_1573062249_read_5</action_id>
                  <action_type>set_permission</action_type>
                  <asset>[[output://create_metadata_field_text_1573062249.assetid]]</asset>
                  <permission>1</permission>
                  <granted>1</granted>
                  <userid>[[system://public_user]]</userid>
              </action>
              
              <action>
                  <action_id>create_metadata_field_wysiwyg_5753977227</action_id>
                  <action_type>create_asset</action_type>
                  <type_code>metadata_field_wysiwyg</type_code>
                  <link_type>2</link_type>
                  <parentid>[[output://create_Metadata_Section_752087999.assetid]]</parentid>
                  <value></value>
                  <is_dependant>1</is_dependant>
                  <is_exclusive>0</is_exclusive>
              </action> 
              <action>
                  <action_id>set_metadata_field_wysiwyg_5753977227_name</action_id>
                  <action_type>set_attribute_value</action_type>
                  <asset>[[output://create_metadata_field_wysiwyg_5753977227.assetid]]</asset>
                  <attribute>name</attribute>
                  <value><![CDATA[abstract]]></value>
              </action>
              <action>
                  <action_id>set_metadata_field_wysiwyg_5753977227_friendly_name</action_id>
                  <action_type>set_attribute_value</action_type>
                  <asset>[[output://create_metadata_field_wysiwyg_5753977227.assetid]]</asset>
                  <attribute>friendly_name</attribute>
                  <value><![CDATA[Abstract]]></value>
              </action>
              <action>
                  <action_id>set_metadata_field_wysiwyg_5753977227_default</action_id>
                  <action_type>set_attribute_value</action_type>
                  <asset>[[output://create_metadata_field_wysiwyg_5753977227.assetid]]</asset>
                  <attribute>default</attribute>
                  <value><![CDATA[Lorem ipsum dolor sit amet, consectetur adipiscing elit, sed do eiusmod tempor incididunt ut labore et dolore magna aliqua. Ut enim ad minim veniam, quis nostrud exercitation ullamco laboris nisi ut aliquip ex ea commodo consequat.]]></value>
              </action>
              <action>
                  <action_id>set_metadata_field_wysiwyg_5753977227_description</action_id>
                  <action_type>set_attribute_value</action_type>
                  <asset>[[output://create_metadata_field_wysiwyg_5753977227.assetid]]</asset>
                  <attribute>description</attribute>
                  <value><![CDATA[]]></value>
              </action>
              <action>
                  <action_id>set_metadata_field_wysiwyg_5753977227_editable</action_id>
                  <action_type>set_attribute_value</action_type>
                  <asset>[[output://create_metadata_field_wysiwyg_5753977227.assetid]]</asset>
                  <attribute>editable</attribute>
                  <value><![CDATA[1]]></value>
              </action>
              <action>
                  <action_id>set_metadata_field_wysiwyg_5753977227_editable</action_id>
                  <action_type>set_attribute_value</action_type>
                  <asset>[[output://create_metadata_field_wysiwyg_5753977227.assetid]]</asset>
                  <attribute>editable</attribute>
                  <value><![CDATA[1]]></value>
              </action>
              <action>
                  <action_id>set_metadata_field_wysiwyg_5753977227_required</action_id>
                  <action_type>set_attribute_value</action_type>
                  <asset>[[output://create_metadata_field_wysiwyg_5753977227.assetid]]</asset>
                  <attribute>required</attribute>
                  <value><![CDATA[0]]></value>
              </action>
              <action>
                  <action_id>set_permission_5753977227_read_5</action_id>
                  <action_type>set_permission</action_type>
                  <asset>[[output://create_metadata_field_wysiwyg_5753977227.assetid]]</asset>
                  <permission>1</permission>
                  <granted>1</granted>
                  <userid>[[system://public_user]]</userid>
              </action>
              
              <action>
                  <action_id>create_metadata_field_wysiwyg_9183890000</action_id>
                  <action_type>create_asset</action_type>
                  <type_code>metadata_field_wysiwyg</type_code>
                  <link_type>2</link_type>
                  <parentid>[[output://create_Metadata_Section_752087999.assetid]]</parentid>
                  <value></value>
                  <is_dependant>1</is_dependant>
                  <is_exclusive>0</is_exclusive>
              </action> 
              <action>
                  <action_id>set_metadata_field_wysiwyg_9183890000_name</action_id>
                  <action_type>set_attribute_value</action_type>
                  <asset>[[output://create_metadata_field_wysiwyg_9183890000.assetid]]</asset>
                  <attribute>name</attribute>
                  <value><![CDATA[body]]></value>
              </action>
              <action>
                  <action_id>set_metadata_field_wysiwyg_9183890000_friendly_name</action_id>
                  <action_type>set_attribute_value</action_type>
                  <asset>[[output://create_metadata_field_wysiwyg_9183890000.assetid]]</asset>
                  <attribute>friendly_name</attribute>
                  <value><![CDATA[Body]]></value>
              </action>
              <action>
                  <action_id>set_metadata_field_wysiwyg_9183890000_default</action_id>
                  <action_type>set_attribute_value</action_type>
                  <asset>[[output://create_metadata_field_wysiwyg_9183890000.assetid]]</asset>
                  <attribute>default</attribute>
                  <value><![CDATA[Lorem ipsum dolor sit amet, <a href='https://google.com'> consectetur adipiscing </a> elit, sed do eiusmod tempor incididunt ut labore et dolore magna aliqua. Ut enim ad minim veniam, quis nostrud exercitation ullamco laboris nisi ut aliquip ex ea commodo consequat.]]></value>
              </action>
              <action>
                  <action_id>set_metadata_field_wysiwyg_9183890000_description</action_id>
                  <action_type>set_attribute_value</action_type>
                  <asset>[[output://create_metadata_field_wysiwyg_9183890000.assetid]]</asset>
                  <attribute>description</attribute>
                  <value><![CDATA[]]></value>
              </action>
              <action>
                  <action_id>set_metadata_field_wysiwyg_9183890000_editable</action_id>
                  <action_type>set_attribute_value</action_type>
                  <asset>[[output://create_metadata_field_wysiwyg_9183890000.assetid]]</asset>
                  <attribute>editable</attribute>
                  <value><![CDATA[1]]></value>
              </action>
              <action>
                  <action_id>set_metadata_field_wysiwyg_9183890000_editable</action_id>
                  <action_type>set_attribute_value</action_type>
                  <asset>[[output://create_metadata_field_wysiwyg_9183890000.assetid]]</asset>
                  <attribute>editable</attribute>
                  <value><![CDATA[1]]></value>
              </action>
              <action>
                  <action_id>set_metadata_field_wysiwyg_9183890000_required</action_id>
                  <action_type>set_attribute_value</action_type>
                  <asset>[[output://create_metadata_field_wysiwyg_9183890000.assetid]]</asset>
                  <attribute>required</attribute>
                  <value><![CDATA[0]]></value>
              </action>
              <action>
                  <action_id>set_permission_9183890000_read_5</action_id>
                  <action_type>set_permission</action_type>
                  <asset>[[output://create_metadata_field_wysiwyg_9183890000.assetid]]</asset>
                  <permission>1</permission>
                  <granted>1</granted>
                  <userid>[[system://public_user]]</userid>
              </action>
              
              <action>
                  <action_id>create_metadata_field_select_5303224323</action_id>
                  <action_type>create_asset</action_type>
                  <type_code>metadata_field_select</type_code>
                  <link_type>2</link_type>
                  <parentid>[[output://create_Metadata_Section_752087999.assetid]]</parentid>
                  <value></value>
                  <is_dependant>1</is_dependant>
                  <is_exclusive>0</is_exclusive>
              </action> 
              <action>
                  <action_id>set_metadata_field_select_5303224323_name</action_id>
                  <action_type>set_attribute_value</action_type>
                  <asset>[[output://create_metadata_field_select_5303224323.assetid]]</asset>
                  <attribute>name</attribute>
                  <value><![CDATA[link_type]]></value>
              </action>
              <action>
                  <action_id>set_metadata_field_select_5303224323_friendly_name</action_id>
                  <action_type>set_attribute_value</action_type>
                  <asset>[[output://create_metadata_field_select_5303224323.assetid]]</asset>
                  <attribute>friendly_name</attribute>
                  <value><![CDATA[Link Type]]></value>
              </action>
              <action>
                  <action_id>set_metadata_field_select_5303224323_default</action_id>
                  <action_type>set_attribute_value</action_type>
                  <asset>[[output://create_metadata_field_select_5303224323.assetid]]</asset>
                  <attribute>default</attribute>
                  <value><![CDATA[button]]></value>
              </action>
              <action>
                  <action_id>set_metadata_field_select_5303224323_description</action_id>
                  <action_type>set_attribute_value</action_type>
                  <asset>[[output://create_metadata_field_select_5303224323.assetid]]</asset>
                  <attribute>description</attribute>
                  <value><![CDATA[]]></value>
              </action>
              <action>
                  <action_id>set_metadata_field_select_5303224323_editable</action_id>
                  <action_type>set_attribute_value</action_type>
                  <asset>[[output://create_metadata_field_select_5303224323.assetid]]</asset>
                  <attribute>editable</attribute>
                  <value><![CDATA[1]]></value>
              </action>
              <action>
                  <action_id>set_metadata_field_select_5303224323_editable</action_id>
                  <action_type>set_attribute_value</action_type>
                  <asset>[[output://create_metadata_field_select_5303224323.assetid]]</asset>
                  <attribute>editable</attribute>
                  <value><![CDATA[1]]></value>
              </action>
              <action>
                  <action_id>set_metadata_field_select_5303224323_required</action_id>
                  <action_type>set_attribute_value</action_type>
                  <asset>[[output://create_metadata_field_select_5303224323.assetid]]</asset>
                  <attribute>required</attribute>
                  <value><![CDATA[0]]></value>
              </action>
              <action>
                  <action_id>set_permission_5303224323_read_5</action_id>
                  <action_type>set_permission</action_type>
                  <asset>[[output://create_metadata_field_select_5303224323.assetid]]</asset>
                  <permission>1</permission>
                  <granted>1</granted>
                  <userid>[[system://public_user]]</userid>
              </action>
              
                  <action>
                      <action_id>set_metadata_field_select_5303224323_select_options</action_id>
                      <action_type>set_attribute_value</action_type>
                      <asset>[[output://create_metadata_field_select_5303224323.assetid]]</asset>
                      <attribute>select_options</attribute>
                      <value><![CDATA[array ('cta' => 'CTA','button' => 'Button',);]]></value>
                  </action>
                  <action>
                      <action_id>set_{f.type}_5303224323_edit_params</action_id>
                      <action_type>set_attribute_value</action_type>
                      <asset>[[output://create_metadata_field_select_5303224323.assetid]]</asset>
                      <attribute>edit_params</attribute>
                      <value><![CDATA[array (
                      'style' => 'list',
                      'type' => 'table',
                      'height' => '',
                      'columns' => '1',
                      'empty_text' => '',
                      'extras' => '',
                      );]]></value>
                  </action>  
                  
              <action>
                  <action_id>create_metadata_field_text_5450787429</action_id>
                  <action_type>create_asset</action_type>
                  <type_code>metadata_field_text</type_code>
                  <link_type>2</link_type>
                  <parentid>[[output://create_Metadata_Section_752087999.assetid]]</parentid>
                  <value></value>
                  <is_dependant>1</is_dependant>
                  <is_exclusive>0</is_exclusive>
              </action> 
              <action>
                  <action_id>set_metadata_field_text_5450787429_name</action_id>
                  <action_type>set_attribute_value</action_type>
                  <asset>[[output://create_metadata_field_text_5450787429.assetid]]</asset>
                  <attribute>name</attribute>
                  <value><![CDATA[cta_link_title]]></value>
              </action>
              <action>
                  <action_id>set_metadata_field_text_5450787429_friendly_name</action_id>
                  <action_type>set_attribute_value</action_type>
                  <asset>[[output://create_metadata_field_text_5450787429.assetid]]</asset>
                  <attribute>friendly_name</attribute>
                  <value><![CDATA[CTA Title]]></value>
              </action>
              <action>
                  <action_id>set_metadata_field_text_5450787429_default</action_id>
                  <action_type>set_attribute_value</action_type>
                  <asset>[[output://create_metadata_field_text_5450787429.assetid]]</asset>
                  <attribute>default</attribute>
                  <value><![CDATA[Find out more]]></value>
              </action>
              <action>
                  <action_id>set_metadata_field_text_5450787429_description</action_id>
                  <action_type>set_attribute_value</action_type>
                  <asset>[[output://create_metadata_field_text_5450787429.assetid]]</asset>
                  <attribute>description</attribute>
                  <value><![CDATA[]]></value>
              </action>
              <action>
                  <action_id>set_metadata_field_text_5450787429_editable</action_id>
                  <action_type>set_attribute_value</action_type>
                  <asset>[[output://create_metadata_field_text_5450787429.assetid]]</asset>
                  <attribute>editable</attribute>
                  <value><![CDATA[1]]></value>
              </action>
              <action>
                  <action_id>set_metadata_field_text_5450787429_editable</action_id>
                  <action_type>set_attribute_value</action_type>
                  <asset>[[output://create_metadata_field_text_5450787429.assetid]]</asset>
                  <attribute>editable</attribute>
                  <value><![CDATA[1]]></value>
              </action>
              <action>
                  <action_id>set_metadata_field_text_5450787429_required</action_id>
                  <action_type>set_attribute_value</action_type>
                  <asset>[[output://create_metadata_field_text_5450787429.assetid]]</asset>
                  <attribute>required</attribute>
                  <value><![CDATA[0]]></value>
              </action>
              <action>
                  <action_id>set_permission_5450787429_read_5</action_id>
                  <action_type>set_permission</action_type>
                  <asset>[[output://create_metadata_field_text_5450787429.assetid]]</asset>
                  <permission>1</permission>
                  <granted>1</granted>
                  <userid>[[system://public_user]]</userid>
              </action>
              
              <action>
                  <action_id>create_metadata_field_related_asset_6575583983</action_id>
                  <action_type>create_asset</action_type>
                  <type_code>metadata_field_related_asset</type_code>
                  <link_type>2</link_type>
                  <parentid>[[output://create_Metadata_Section_752087999.assetid]]</parentid>
                  <value></value>
                  <is_dependant>1</is_dependant>
                  <is_exclusive>0</is_exclusive>
              </action> 
              <action>
                  <action_id>set_metadata_field_related_asset_6575583983_name</action_id>
                  <action_type>set_attribute_value</action_type>
                  <asset>[[output://create_metadata_field_related_asset_6575583983.assetid]]</asset>
                  <attribute>name</attribute>
                  <value><![CDATA[cta_link]]></value>
              </action>
              <action>
                  <action_id>set_metadata_field_related_asset_6575583983_friendly_name</action_id>
                  <action_type>set_attribute_value</action_type>
                  <asset>[[output://create_metadata_field_related_asset_6575583983.assetid]]</asset>
                  <attribute>friendly_name</attribute>
                  <value><![CDATA[CTA Link]]></value>
              </action>
              <action>
                  <action_id>set_metadata_field_related_asset_6575583983_default</action_id>
                  <action_type>set_attribute_value</action_type>
                  <asset>[[output://create_metadata_field_related_asset_6575583983.assetid]]</asset>
                  <attribute>default</attribute>
                  <value><![CDATA[https://health.qld.gov.au]]></value>
              </action>
              <action>
                  <action_id>set_metadata_field_related_asset_6575583983_description</action_id>
                  <action_type>set_attribute_value</action_type>
                  <asset>[[output://create_metadata_field_related_asset_6575583983.assetid]]</asset>
                  <attribute>description</attribute>
                  <value><![CDATA[]]></value>
              </action>
              <action>
                  <action_id>set_metadata_field_related_asset_6575583983_editable</action_id>
                  <action_type>set_attribute_value</action_type>
                  <asset>[[output://create_metadata_field_related_asset_6575583983.assetid]]</asset>
                  <attribute>editable</attribute>
                  <value><![CDATA[1]]></value>
              </action>
              <action>
                  <action_id>set_metadata_field_related_asset_6575583983_editable</action_id>
                  <action_type>set_attribute_value</action_type>
                  <asset>[[output://create_metadata_field_related_asset_6575583983.assetid]]</asset>
                  <attribute>editable</attribute>
                  <value><![CDATA[1]]></value>
              </action>
              <action>
                  <action_id>set_metadata_field_related_asset_6575583983_required</action_id>
                  <action_type>set_attribute_value</action_type>
                  <asset>[[output://create_metadata_field_related_asset_6575583983.assetid]]</asset>
                  <attribute>required</attribute>
                  <value><![CDATA[0]]></value>
              </action>
              <action>
                  <action_id>set_permission_6575583983_read_5</action_id>
                  <action_type>set_permission</action_type>
                  <asset>[[output://create_metadata_field_related_asset_6575583983.assetid]]</asset>
                  <permission>1</permission>
                  <granted>1</granted>
                  <userid>[[system://public_user]]</userid>
              </action>
              
              <action>
                  <action_id>create_metadata_field_text_7837378883</action_id>
                  <action_type>create_asset</action_type>
                  <type_code>metadata_field_text</type_code>
                  <link_type>2</link_type>
                  <parentid>[[output://create_Metadata_Section_752087999.assetid]]</parentid>
                  <value></value>
                  <is_dependant>1</is_dependant>
                  <is_exclusive>0</is_exclusive>
              </action> 
              <action>
                  <action_id>set_metadata_field_text_7837378883_name</action_id>
                  <action_type>set_attribute_value</action_type>
                  <asset>[[output://create_metadata_field_text_7837378883.assetid]]</asset>
                  <attribute>name</attribute>
                  <value><![CDATA[primary_link_title]]></value>
              </action>
              <action>
                  <action_id>set_metadata_field_text_7837378883_friendly_name</action_id>
                  <action_type>set_attribute_value</action_type>
                  <asset>[[output://create_metadata_field_text_7837378883.assetid]]</asset>
                  <attribute>friendly_name</attribute>
                  <value><![CDATA[Primary Button Title]]></value>
              </action>
              <action>
                  <action_id>set_metadata_field_text_7837378883_default</action_id>
                  <action_type>set_attribute_value</action_type>
                  <asset>[[output://create_metadata_field_text_7837378883.assetid]]</asset>
                  <attribute>default</attribute>
                  <value><![CDATA[label]]></value>
              </action>
              <action>
                  <action_id>set_metadata_field_text_7837378883_description</action_id>
                  <action_type>set_attribute_value</action_type>
                  <asset>[[output://create_metadata_field_text_7837378883.assetid]]</asset>
                  <attribute>description</attribute>
                  <value><![CDATA[]]></value>
              </action>
              <action>
                  <action_id>set_metadata_field_text_7837378883_editable</action_id>
                  <action_type>set_attribute_value</action_type>
                  <asset>[[output://create_metadata_field_text_7837378883.assetid]]</asset>
                  <attribute>editable</attribute>
                  <value><![CDATA[1]]></value>
              </action>
              <action>
                  <action_id>set_metadata_field_text_7837378883_editable</action_id>
                  <action_type>set_attribute_value</action_type>
                  <asset>[[output://create_metadata_field_text_7837378883.assetid]]</asset>
                  <attribute>editable</attribute>
                  <value><![CDATA[1]]></value>
              </action>
              <action>
                  <action_id>set_metadata_field_text_7837378883_required</action_id>
                  <action_type>set_attribute_value</action_type>
                  <asset>[[output://create_metadata_field_text_7837378883.assetid]]</asset>
                  <attribute>required</attribute>
                  <value><![CDATA[0]]></value>
              </action>
              <action>
                  <action_id>set_permission_7837378883_read_5</action_id>
                  <action_type>set_permission</action_type>
                  <asset>[[output://create_metadata_field_text_7837378883.assetid]]</asset>
                  <permission>1</permission>
                  <granted>1</granted>
                  <userid>[[system://public_user]]</userid>
              </action>
              
              <action>
                  <action_id>create_metadata_field_related_asset_7115284012</action_id>
                  <action_type>create_asset</action_type>
                  <type_code>metadata_field_related_asset</type_code>
                  <link_type>2</link_type>
                  <parentid>[[output://create_Metadata_Section_752087999.assetid]]</parentid>
                  <value></value>
                  <is_dependant>1</is_dependant>
                  <is_exclusive>0</is_exclusive>
              </action> 
              <action>
                  <action_id>set_metadata_field_related_asset_7115284012_name</action_id>
                  <action_type>set_attribute_value</action_type>
                  <asset>[[output://create_metadata_field_related_asset_7115284012.assetid]]</asset>
                  <attribute>name</attribute>
                  <value><![CDATA[primary_link]]></value>
              </action>
              <action>
                  <action_id>set_metadata_field_related_asset_7115284012_friendly_name</action_id>
                  <action_type>set_attribute_value</action_type>
                  <asset>[[output://create_metadata_field_related_asset_7115284012.assetid]]</asset>
                  <attribute>friendly_name</attribute>
                  <value><![CDATA[Primary Button Link]]></value>
              </action>
              <action>
                  <action_id>set_metadata_field_related_asset_7115284012_default</action_id>
                  <action_type>set_attribute_value</action_type>
                  <asset>[[output://create_metadata_field_related_asset_7115284012.assetid]]</asset>
                  <attribute>default</attribute>
                  <value><![CDATA[https://health.qld.gov.au]]></value>
              </action>
              <action>
                  <action_id>set_metadata_field_related_asset_7115284012_description</action_id>
                  <action_type>set_attribute_value</action_type>
                  <asset>[[output://create_metadata_field_related_asset_7115284012.assetid]]</asset>
                  <attribute>description</attribute>
                  <value><![CDATA[]]></value>
              </action>
              <action>
                  <action_id>set_metadata_field_related_asset_7115284012_editable</action_id>
                  <action_type>set_attribute_value</action_type>
                  <asset>[[output://create_metadata_field_related_asset_7115284012.assetid]]</asset>
                  <attribute>editable</attribute>
                  <value><![CDATA[1]]></value>
              </action>
              <action>
                  <action_id>set_metadata_field_related_asset_7115284012_editable</action_id>
                  <action_type>set_attribute_value</action_type>
                  <asset>[[output://create_metadata_field_related_asset_7115284012.assetid]]</asset>
                  <attribute>editable</attribute>
                  <value><![CDATA[1]]></value>
              </action>
              <action>
                  <action_id>set_metadata_field_related_asset_7115284012_required</action_id>
                  <action_type>set_attribute_value</action_type>
                  <asset>[[output://create_metadata_field_related_asset_7115284012.assetid]]</asset>
                  <attribute>required</attribute>
                  <value><![CDATA[0]]></value>
              </action>
              <action>
                  <action_id>set_permission_7115284012_read_5</action_id>
                  <action_type>set_permission</action_type>
                  <asset>[[output://create_metadata_field_related_asset_7115284012.assetid]]</asset>
                  <permission>1</permission>
                  <granted>1</granted>
                  <userid>[[system://public_user]]</userid>
              </action>
              
              <action>
                  <action_id>create_metadata_field_text_1064568039</action_id>
                  <action_type>create_asset</action_type>
                  <type_code>metadata_field_text</type_code>
                  <link_type>2</link_type>
                  <parentid>[[output://create_Metadata_Section_752087999.assetid]]</parentid>
                  <value></value>
                  <is_dependant>1</is_dependant>
                  <is_exclusive>0</is_exclusive>
              </action> 
              <action>
                  <action_id>set_metadata_field_text_1064568039_name</action_id>
                  <action_type>set_attribute_value</action_type>
                  <asset>[[output://create_metadata_field_text_1064568039.assetid]]</asset>
                  <attribute>name</attribute>
                  <value><![CDATA[secondary_link_title]]></value>
              </action>
              <action>
                  <action_id>set_metadata_field_text_1064568039_friendly_name</action_id>
                  <action_type>set_attribute_value</action_type>
                  <asset>[[output://create_metadata_field_text_1064568039.assetid]]</asset>
                  <attribute>friendly_name</attribute>
                  <value><![CDATA[Secondary Button Title]]></value>
              </action>
              <action>
                  <action_id>set_metadata_field_text_1064568039_default</action_id>
                  <action_type>set_attribute_value</action_type>
                  <asset>[[output://create_metadata_field_text_1064568039.assetid]]</asset>
                  <attribute>default</attribute>
                  <value><![CDATA[label]]></value>
              </action>
              <action>
                  <action_id>set_metadata_field_text_1064568039_description</action_id>
                  <action_type>set_attribute_value</action_type>
                  <asset>[[output://create_metadata_field_text_1064568039.assetid]]</asset>
                  <attribute>description</attribute>
                  <value><![CDATA[]]></value>
              </action>
              <action>
                  <action_id>set_metadata_field_text_1064568039_editable</action_id>
                  <action_type>set_attribute_value</action_type>
                  <asset>[[output://create_metadata_field_text_1064568039.assetid]]</asset>
                  <attribute>editable</attribute>
                  <value><![CDATA[1]]></value>
              </action>
              <action>
                  <action_id>set_metadata_field_text_1064568039_editable</action_id>
                  <action_type>set_attribute_value</action_type>
                  <asset>[[output://create_metadata_field_text_1064568039.assetid]]</asset>
                  <attribute>editable</attribute>
                  <value><![CDATA[1]]></value>
              </action>
              <action>
                  <action_id>set_metadata_field_text_1064568039_required</action_id>
                  <action_type>set_attribute_value</action_type>
                  <asset>[[output://create_metadata_field_text_1064568039.assetid]]</asset>
                  <attribute>required</attribute>
                  <value><![CDATA[0]]></value>
              </action>
              <action>
                  <action_id>set_permission_1064568039_read_5</action_id>
                  <action_type>set_permission</action_type>
                  <asset>[[output://create_metadata_field_text_1064568039.assetid]]</asset>
                  <permission>1</permission>
                  <granted>1</granted>
                  <userid>[[system://public_user]]</userid>
              </action>
              
              <action>
                  <action_id>create_metadata_field_related_asset_4033882367</action_id>
                  <action_type>create_asset</action_type>
                  <type_code>metadata_field_related_asset</type_code>
                  <link_type>2</link_type>
                  <parentid>[[output://create_Metadata_Section_752087999.assetid]]</parentid>
                  <value></value>
                  <is_dependant>1</is_dependant>
                  <is_exclusive>0</is_exclusive>
              </action> 
              <action>
                  <action_id>set_metadata_field_related_asset_4033882367_name</action_id>
                  <action_type>set_attribute_value</action_type>
                  <asset>[[output://create_metadata_field_related_asset_4033882367.assetid]]</asset>
                  <attribute>name</attribute>
                  <value><![CDATA[secondary_link]]></value>
              </action>
              <action>
                  <action_id>set_metadata_field_related_asset_4033882367_friendly_name</action_id>
                  <action_type>set_attribute_value</action_type>
                  <asset>[[output://create_metadata_field_related_asset_4033882367.assetid]]</asset>
                  <attribute>friendly_name</attribute>
                  <value><![CDATA[Secondary Button Link]]></value>
              </action>
              <action>
                  <action_id>set_metadata_field_related_asset_4033882367_default</action_id>
                  <action_type>set_attribute_value</action_type>
                  <asset>[[output://create_metadata_field_related_asset_4033882367.assetid]]</asset>
                  <attribute>default</attribute>
                  <value><![CDATA[https://health.qld.gov.au]]></value>
              </action>
              <action>
                  <action_id>set_metadata_field_related_asset_4033882367_description</action_id>
                  <action_type>set_attribute_value</action_type>
                  <asset>[[output://create_metadata_field_related_asset_4033882367.assetid]]</asset>
                  <attribute>description</attribute>
                  <value><![CDATA[]]></value>
              </action>
              <action>
                  <action_id>set_metadata_field_related_asset_4033882367_editable</action_id>
                  <action_type>set_attribute_value</action_type>
                  <asset>[[output://create_metadata_field_related_asset_4033882367.assetid]]</asset>
                  <attribute>editable</attribute>
                  <value><![CDATA[1]]></value>
              </action>
              <action>
                  <action_id>set_metadata_field_related_asset_4033882367_editable</action_id>
                  <action_type>set_attribute_value</action_type>
                  <asset>[[output://create_metadata_field_related_asset_4033882367.assetid]]</asset>
                  <attribute>editable</attribute>
                  <value><![CDATA[1]]></value>
              </action>
              <action>
                  <action_id>set_metadata_field_related_asset_4033882367_required</action_id>
                  <action_type>set_attribute_value</action_type>
                  <asset>[[output://create_metadata_field_related_asset_4033882367.assetid]]</asset>
                  <attribute>required</attribute>
                  <value><![CDATA[0]]></value>
              </action>
              <action>
                  <action_id>set_permission_4033882367_read_5</action_id>
                  <action_type>set_permission</action_type>
                  <asset>[[output://create_metadata_field_related_asset_4033882367.assetid]]</asset>
                  <permission>1</permission>
                  <granted>1</granted>
                  <userid>[[system://public_user]]</userid>
              </action>
              </actions>