<?xml version="1.0" encoding="utf-8"?>
          <actions>
          <action>
            <action_id>create_Content_Container_Template_8616087459</action_id>
            <action_type>create_asset</action_type>
            <type_code>Content_Container_Template</type_code>
            <link_type>1</link_type>
            <parentid>1</parentid>
            <value></value>
            <is_dependant>0</is_dependant>
            <is_exclusive>0</is_exclusive>
          </action>
          <action>
            <action_id>set_Content_Container_Template_8616087459_name</action_id>
            <action_type>set_attribute_value</action_type>
            <asset>[[output://create_Content_Container_Template_8616087459.assetid]]</asset>
            <attribute>name</attribute>
            <value><![CDATA[Banner - Intermediate]]></value>
          </action>

          <action>
            <action_id>set_Content_Container_Template_8616087459_edit_interface_in_admin</action_id>
            <action_type>set_attribute_value</action_type>
            <asset>[[output://create_Content_Container_Template_8616087459.assetid]]</asset>
            <attribute>edit_interface_in_admin</attribute>
            <value><![CDATA[1]]></value>
          </action>

          <action>
            <action_id>set_Content_Container_Template_8616087459_icon_color</action_id>
            <action_type>set_attribute_value</action_type>
            <asset>[[output://create_Content_Container_Template_8616087459.assetid]]</asset>
            <attribute>icon_color</attribute>
            <value><![CDATA[blue]]></value>
          </action>
          
          <action>
          <action_id>create_Metadata_Schema_9391131037</action_id>
          <action_type>create_asset</action_type>
          <type_code>Metadata_Schema</type_code>
          <link_type>1</link_type>
          <parentid>[[output://create_Content_Container_Template_8616087459.assetid]]</parentid>
          <value></value>
          <is_dependant>0</is_dependant>
          <is_exclusive>0</is_exclusive>
          </action>
          <action>
            <action_id>set_Metadata_Schema_9391131037_name</action_id>
            <action_type>set_attribute_value</action_type>
            <asset>[[output://create_Metadata_Schema_9391131037.assetid]]</asset>
            <attribute>name</attribute>
            <value><![CDATA[Banner - Intermediate]]></value>
          </action>
          <action>
              <action_id>set_permission_9391131037_read_5</action_id>
              <action_type>set_permission</action_type>
              <asset>[[output://create_Metadata_Schema_9391131037.assetid]]</asset>
              <permission>1</permission>
              <granted>1</granted>
              <userid>[[system://public_user]]</userid>
          </action>
          
          <action>
            <action_id>create_Metadata_Section_3563465437</action_id>
            <action_type>create_asset</action_type>
            <type_code>Metadata_Section</type_code>
            <link_type>2</link_type>
            <parentid>[[output://create_Metadata_Schema_9391131037.assetid]]</parentid>
            <value></value>
            <is_dependant>1</is_dependant>
            <is_exclusive>0</is_exclusive>
          </action>
          <action>
            <action_id>add_Metadata_Section_3563465437_path</action_id>
            <action_type>add_web_path</action_type>
            <asset>[[output://create_Metadata_Section_3563465437.assetid]]</asset>
            <parent_asset>[[output://create_Metadata_Schema_9391131037.assetid]]</parent_asset>
            <path>settings</path>
          </action>
          <action>
            <action_id>set_Metadata_Section_3563465437_name</action_id>
            <action_type>set_attribute_value</action_type>
            <asset>[[output://create_Metadata_Section_3563465437.assetid]]</asset>
            <attribute>name</attribute>
            <value><![CDATA[Settings]]></value>
          </action>
          <action>
              <action_id>set_permission_3563465437_read_5</action_id>
              <action_type>set_permission</action_type>
              <asset>[[output://create_Metadata_Section_3563465437.assetid]]</asset>
              <permission>1</permission>
              <granted>1</granted>
              <userid>[[system://public_user]]</userid>
          </action>           
          
              <action>
                  <action_id>create_metadata_field_select_7396611077</action_id>
                  <action_type>create_asset</action_type>
                  <type_code>metadata_field_select</type_code>
                  <link_type>2</link_type>
                  <parentid>[[output://create_Metadata_Section_3563465437.assetid]]</parentid>
                  <value></value>
                  <is_dependant>1</is_dependant>
                  <is_exclusive>0</is_exclusive>
              </action> 
              <action>
                  <action_id>set_metadata_field_select_7396611077_name</action_id>
                  <action_type>set_attribute_value</action_type>
                  <asset>[[output://create_metadata_field_select_7396611077.assetid]]</asset>
                  <attribute>name</attribute>
                  <value><![CDATA[breadcrumbs_display]]></value>
              </action>
              <action>
                  <action_id>set_metadata_field_select_7396611077_friendly_name</action_id>
                  <action_type>set_attribute_value</action_type>
                  <asset>[[output://create_metadata_field_select_7396611077.assetid]]</asset>
                  <attribute>friendly_name</attribute>
                  <value><![CDATA[Display Breadcrumbs?]]></value>
              </action>
              <action>
                  <action_id>set_metadata_field_select_7396611077_default</action_id>
                  <action_type>set_attribute_value</action_type>
                  <asset>[[output://create_metadata_field_select_7396611077.assetid]]</asset>
                  <attribute>default</attribute>
                  <value><![CDATA[yes]]></value>
              </action>
              <action>
                  <action_id>set_metadata_field_select_7396611077_description</action_id>
                  <action_type>set_attribute_value</action_type>
                  <asset>[[output://create_metadata_field_select_7396611077.assetid]]</asset>
                  <attribute>description</attribute>
                  <value><![CDATA[]]></value>
              </action>
              <action>
                  <action_id>set_metadata_field_select_7396611077_editable</action_id>
                  <action_type>set_attribute_value</action_type>
                  <asset>[[output://create_metadata_field_select_7396611077.assetid]]</asset>
                  <attribute>editable</attribute>
                  <value><![CDATA[1]]></value>
              </action>
              <action>
                  <action_id>set_metadata_field_select_7396611077_editable</action_id>
                  <action_type>set_attribute_value</action_type>
                  <asset>[[output://create_metadata_field_select_7396611077.assetid]]</asset>
                  <attribute>editable</attribute>
                  <value><![CDATA[1]]></value>
              </action>
              <action>
                  <action_id>set_metadata_field_select_7396611077_required</action_id>
                  <action_type>set_attribute_value</action_type>
                  <asset>[[output://create_metadata_field_select_7396611077.assetid]]</asset>
                  <attribute>required</attribute>
                  <value><![CDATA[0]]></value>
              </action>
              <action>
                  <action_id>set_permission_7396611077_read_5</action_id>
                  <action_type>set_permission</action_type>
                  <asset>[[output://create_metadata_field_select_7396611077.assetid]]</asset>
                  <permission>1</permission>
                  <granted>1</granted>
                  <userid>[[system://public_user]]</userid>
              </action>
              
                  <action>
                      <action_id>set_metadata_field_select_7396611077_select_options</action_id>
                      <action_type>set_attribute_value</action_type>
                      <asset>[[output://create_metadata_field_select_7396611077.assetid]]</asset>
                      <attribute>select_options</attribute>
                      <value><![CDATA[array ('' => 'No','yes' => 'Yes',);]]></value>
                  </action>
                  <action>
                      <action_id>set_{f.type}_7396611077_edit_params</action_id>
                      <action_type>set_attribute_value</action_type>
                      <asset>[[output://create_metadata_field_select_7396611077.assetid]]</asset>
                      <attribute>edit_params</attribute>
                      <value><![CDATA[array (
                      'style' => 'list',
                      'type' => 'table',
                      'height' => '',
                      'columns' => '1',
                      'empty_text' => '',
                      'extras' => '',
                      );]]></value>
                  </action>  
                  
              <action>
                  <action_id>create_metadata_field_text_6490235627</action_id>
                  <action_type>create_asset</action_type>
                  <type_code>metadata_field_text</type_code>
                  <link_type>2</link_type>
                  <parentid>[[output://create_Metadata_Section_3563465437.assetid]]</parentid>
                  <value></value>
                  <is_dependant>1</is_dependant>
                  <is_exclusive>0</is_exclusive>
              </action> 
              <action>
                  <action_id>set_metadata_field_text_6490235627_name</action_id>
                  <action_type>set_attribute_value</action_type>
                  <asset>[[output://create_metadata_field_text_6490235627.assetid]]</asset>
                  <attribute>name</attribute>
                  <value><![CDATA[heading_primary]]></value>
              </action>
              <action>
                  <action_id>set_metadata_field_text_6490235627_friendly_name</action_id>
                  <action_type>set_attribute_value</action_type>
                  <asset>[[output://create_metadata_field_text_6490235627.assetid]]</asset>
                  <attribute>friendly_name</attribute>
                  <value><![CDATA[Primary Heading]]></value>
              </action>
              <action>
                  <action_id>set_metadata_field_text_6490235627_default</action_id>
                  <action_type>set_attribute_value</action_type>
                  <asset>[[output://create_metadata_field_text_6490235627.assetid]]</asset>
                  <attribute>default</attribute>
                  <value><![CDATA[Banner Intermediate]]></value>
              </action>
              <action>
                  <action_id>set_metadata_field_text_6490235627_description</action_id>
                  <action_type>set_attribute_value</action_type>
                  <asset>[[output://create_metadata_field_text_6490235627.assetid]]</asset>
                  <attribute>description</attribute>
                  <value><![CDATA[]]></value>
              </action>
              <action>
                  <action_id>set_metadata_field_text_6490235627_editable</action_id>
                  <action_type>set_attribute_value</action_type>
                  <asset>[[output://create_metadata_field_text_6490235627.assetid]]</asset>
                  <attribute>editable</attribute>
                  <value><![CDATA[1]]></value>
              </action>
              <action>
                  <action_id>set_metadata_field_text_6490235627_editable</action_id>
                  <action_type>set_attribute_value</action_type>
                  <asset>[[output://create_metadata_field_text_6490235627.assetid]]</asset>
                  <attribute>editable</attribute>
                  <value><![CDATA[1]]></value>
              </action>
              <action>
                  <action_id>set_metadata_field_text_6490235627_required</action_id>
                  <action_type>set_attribute_value</action_type>
                  <asset>[[output://create_metadata_field_text_6490235627.assetid]]</asset>
                  <attribute>required</attribute>
                  <value><![CDATA[0]]></value>
              </action>
              <action>
                  <action_id>set_permission_6490235627_read_5</action_id>
                  <action_type>set_permission</action_type>
                  <asset>[[output://create_metadata_field_text_6490235627.assetid]]</asset>
                  <permission>1</permission>
                  <granted>1</granted>
                  <userid>[[system://public_user]]</userid>
              </action>
              
              <action>
                  <action_id>create_metadata_field_text_8015128180</action_id>
                  <action_type>create_asset</action_type>
                  <type_code>metadata_field_text</type_code>
                  <link_type>2</link_type>
                  <parentid>[[output://create_Metadata_Section_3563465437.assetid]]</parentid>
                  <value></value>
                  <is_dependant>1</is_dependant>
                  <is_exclusive>0</is_exclusive>
              </action> 
              <action>
                  <action_id>set_metadata_field_text_8015128180_name</action_id>
                  <action_type>set_attribute_value</action_type>
                  <asset>[[output://create_metadata_field_text_8015128180.assetid]]</asset>
                  <attribute>name</attribute>
                  <value><![CDATA[heading_secondary]]></value>
              </action>
              <action>
                  <action_id>set_metadata_field_text_8015128180_friendly_name</action_id>
                  <action_type>set_attribute_value</action_type>
                  <asset>[[output://create_metadata_field_text_8015128180.assetid]]</asset>
                  <attribute>friendly_name</attribute>
                  <value><![CDATA[Secondary Heading]]></value>
              </action>
              <action>
                  <action_id>set_metadata_field_text_8015128180_default</action_id>
                  <action_type>set_attribute_value</action_type>
                  <asset>[[output://create_metadata_field_text_8015128180.assetid]]</asset>
                  <attribute>default</attribute>
                  <value><![CDATA[Heading Secondary]]></value>
              </action>
              <action>
                  <action_id>set_metadata_field_text_8015128180_description</action_id>
                  <action_type>set_attribute_value</action_type>
                  <asset>[[output://create_metadata_field_text_8015128180.assetid]]</asset>
                  <attribute>description</attribute>
                  <value><![CDATA[]]></value>
              </action>
              <action>
                  <action_id>set_metadata_field_text_8015128180_editable</action_id>
                  <action_type>set_attribute_value</action_type>
                  <asset>[[output://create_metadata_field_text_8015128180.assetid]]</asset>
                  <attribute>editable</attribute>
                  <value><![CDATA[1]]></value>
              </action>
              <action>
                  <action_id>set_metadata_field_text_8015128180_editable</action_id>
                  <action_type>set_attribute_value</action_type>
                  <asset>[[output://create_metadata_field_text_8015128180.assetid]]</asset>
                  <attribute>editable</attribute>
                  <value><![CDATA[1]]></value>
              </action>
              <action>
                  <action_id>set_metadata_field_text_8015128180_required</action_id>
                  <action_type>set_attribute_value</action_type>
                  <asset>[[output://create_metadata_field_text_8015128180.assetid]]</asset>
                  <attribute>required</attribute>
                  <value><![CDATA[0]]></value>
              </action>
              <action>
                  <action_id>set_permission_8015128180_read_5</action_id>
                  <action_type>set_permission</action_type>
                  <asset>[[output://create_metadata_field_text_8015128180.assetid]]</asset>
                  <permission>1</permission>
                  <granted>1</granted>
                  <userid>[[system://public_user]]</userid>
              </action>
              
              <action>
                  <action_id>create_metadata_field_select_6844099481</action_id>
                  <action_type>create_asset</action_type>
                  <type_code>metadata_field_select</type_code>
                  <link_type>2</link_type>
                  <parentid>[[output://create_Metadata_Section_3563465437.assetid]]</parentid>
                  <value></value>
                  <is_dependant>1</is_dependant>
                  <is_exclusive>0</is_exclusive>
              </action> 
              <action>
                  <action_id>set_metadata_field_select_6844099481_name</action_id>
                  <action_type>set_attribute_value</action_type>
                  <asset>[[output://create_metadata_field_select_6844099481.assetid]]</asset>
                  <attribute>name</attribute>
                  <value><![CDATA[heading_background_display]]></value>
              </action>
              <action>
                  <action_id>set_metadata_field_select_6844099481_friendly_name</action_id>
                  <action_type>set_attribute_value</action_type>
                  <asset>[[output://create_metadata_field_select_6844099481.assetid]]</asset>
                  <attribute>friendly_name</attribute>
                  <value><![CDATA[Display block background?]]></value>
              </action>
              <action>
                  <action_id>set_metadata_field_select_6844099481_default</action_id>
                  <action_type>set_attribute_value</action_type>
                  <asset>[[output://create_metadata_field_select_6844099481.assetid]]</asset>
                  <attribute>default</attribute>
                  <value><![CDATA[no]]></value>
              </action>
              <action>
                  <action_id>set_metadata_field_select_6844099481_description</action_id>
                  <action_type>set_attribute_value</action_type>
                  <asset>[[output://create_metadata_field_select_6844099481.assetid]]</asset>
                  <attribute>description</attribute>
                  <value><![CDATA[]]></value>
              </action>
              <action>
                  <action_id>set_metadata_field_select_6844099481_editable</action_id>
                  <action_type>set_attribute_value</action_type>
                  <asset>[[output://create_metadata_field_select_6844099481.assetid]]</asset>
                  <attribute>editable</attribute>
                  <value><![CDATA[1]]></value>
              </action>
              <action>
                  <action_id>set_metadata_field_select_6844099481_editable</action_id>
                  <action_type>set_attribute_value</action_type>
                  <asset>[[output://create_metadata_field_select_6844099481.assetid]]</asset>
                  <attribute>editable</attribute>
                  <value><![CDATA[1]]></value>
              </action>
              <action>
                  <action_id>set_metadata_field_select_6844099481_required</action_id>
                  <action_type>set_attribute_value</action_type>
                  <asset>[[output://create_metadata_field_select_6844099481.assetid]]</asset>
                  <attribute>required</attribute>
                  <value><![CDATA[0]]></value>
              </action>
              <action>
                  <action_id>set_permission_6844099481_read_5</action_id>
                  <action_type>set_permission</action_type>
                  <asset>[[output://create_metadata_field_select_6844099481.assetid]]</asset>
                  <permission>1</permission>
                  <granted>1</granted>
                  <userid>[[system://public_user]]</userid>
              </action>
              
                  <action>
                      <action_id>set_metadata_field_select_6844099481_select_options</action_id>
                      <action_type>set_attribute_value</action_type>
                      <asset>[[output://create_metadata_field_select_6844099481.assetid]]</asset>
                      <attribute>select_options</attribute>
                      <value><![CDATA[array ('' => 'No','yes' => 'Yes',);]]></value>
                  </action>
                  <action>
                      <action_id>set_{f.type}_6844099481_edit_params</action_id>
                      <action_type>set_attribute_value</action_type>
                      <asset>[[output://create_metadata_field_select_6844099481.assetid]]</asset>
                      <attribute>edit_params</attribute>
                      <value><![CDATA[array (
                      'style' => 'list',
                      'type' => 'table',
                      'height' => '',
                      'columns' => '1',
                      'empty_text' => '',
                      'extras' => '',
                      );]]></value>
                  </action>  
                  
              <action>
                  <action_id>create_metadata_field_wysiwyg_6883083368</action_id>
                  <action_type>create_asset</action_type>
                  <type_code>metadata_field_wysiwyg</type_code>
                  <link_type>2</link_type>
                  <parentid>[[output://create_Metadata_Section_3563465437.assetid]]</parentid>
                  <value></value>
                  <is_dependant>1</is_dependant>
                  <is_exclusive>0</is_exclusive>
              </action> 
              <action>
                  <action_id>set_metadata_field_wysiwyg_6883083368_name</action_id>
                  <action_type>set_attribute_value</action_type>
                  <asset>[[output://create_metadata_field_wysiwyg_6883083368.assetid]]</asset>
                  <attribute>name</attribute>
                  <value><![CDATA[abstract]]></value>
              </action>
              <action>
                  <action_id>set_metadata_field_wysiwyg_6883083368_friendly_name</action_id>
                  <action_type>set_attribute_value</action_type>
                  <asset>[[output://create_metadata_field_wysiwyg_6883083368.assetid]]</asset>
                  <attribute>friendly_name</attribute>
                  <value><![CDATA[Abstract]]></value>
              </action>
              <action>
                  <action_id>set_metadata_field_wysiwyg_6883083368_default</action_id>
                  <action_type>set_attribute_value</action_type>
                  <asset>[[output://create_metadata_field_wysiwyg_6883083368.assetid]]</asset>
                  <attribute>default</attribute>
                  <value><![CDATA[<p>Lorem ipsum dolor sit amet, consectetur adipiscing elit, sed do eiusmod tempor incididunt ut labore et dolore magna aliqua. Ut enim ad minim veniam, quis nostrud exercitation ullamco laboris nisi ut aliquip ex ea commodo consequat.</p>]]></value>
              </action>
              <action>
                  <action_id>set_metadata_field_wysiwyg_6883083368_description</action_id>
                  <action_type>set_attribute_value</action_type>
                  <asset>[[output://create_metadata_field_wysiwyg_6883083368.assetid]]</asset>
                  <attribute>description</attribute>
                  <value><![CDATA[]]></value>
              </action>
              <action>
                  <action_id>set_metadata_field_wysiwyg_6883083368_editable</action_id>
                  <action_type>set_attribute_value</action_type>
                  <asset>[[output://create_metadata_field_wysiwyg_6883083368.assetid]]</asset>
                  <attribute>editable</attribute>
                  <value><![CDATA[1]]></value>
              </action>
              <action>
                  <action_id>set_metadata_field_wysiwyg_6883083368_editable</action_id>
                  <action_type>set_attribute_value</action_type>
                  <asset>[[output://create_metadata_field_wysiwyg_6883083368.assetid]]</asset>
                  <attribute>editable</attribute>
                  <value><![CDATA[1]]></value>
              </action>
              <action>
                  <action_id>set_metadata_field_wysiwyg_6883083368_required</action_id>
                  <action_type>set_attribute_value</action_type>
                  <asset>[[output://create_metadata_field_wysiwyg_6883083368.assetid]]</asset>
                  <attribute>required</attribute>
                  <value><![CDATA[0]]></value>
              </action>
              <action>
                  <action_id>set_permission_6883083368_read_5</action_id>
                  <action_type>set_permission</action_type>
                  <asset>[[output://create_metadata_field_wysiwyg_6883083368.assetid]]</asset>
                  <permission>1</permission>
                  <granted>1</granted>
                  <userid>[[system://public_user]]</userid>
              </action>
              
              <action>
                  <action_id>create_metadata_field_related_asset_5093479889</action_id>
                  <action_type>create_asset</action_type>
                  <type_code>metadata_field_related_asset</type_code>
                  <link_type>2</link_type>
                  <parentid>[[output://create_Metadata_Section_3563465437.assetid]]</parentid>
                  <value></value>
                  <is_dependant>1</is_dependant>
                  <is_exclusive>0</is_exclusive>
              </action> 
              <action>
                  <action_id>set_metadata_field_related_asset_5093479889_name</action_id>
                  <action_type>set_attribute_value</action_type>
                  <asset>[[output://create_metadata_field_related_asset_5093479889.assetid]]</asset>
                  <attribute>name</attribute>
                  <value><![CDATA[hero_image]]></value>
              </action>
              <action>
                  <action_id>set_metadata_field_related_asset_5093479889_friendly_name</action_id>
                  <action_type>set_attribute_value</action_type>
                  <asset>[[output://create_metadata_field_related_asset_5093479889.assetid]]</asset>
                  <attribute>friendly_name</attribute>
                  <value><![CDATA[Image]]></value>
              </action>
              <action>
                  <action_id>set_metadata_field_related_asset_5093479889_default</action_id>
                  <action_type>set_attribute_value</action_type>
                  <asset>[[output://create_metadata_field_related_asset_5093479889.assetid]]</asset>
                  <attribute>default</attribute>
                  <value><![CDATA[https://via.placeholder.com/782x520]]></value>
              </action>
              <action>
                  <action_id>set_metadata_field_related_asset_5093479889_description</action_id>
                  <action_type>set_attribute_value</action_type>
                  <asset>[[output://create_metadata_field_related_asset_5093479889.assetid]]</asset>
                  <attribute>description</attribute>
                  <value><![CDATA[]]></value>
              </action>
              <action>
                  <action_id>set_metadata_field_related_asset_5093479889_editable</action_id>
                  <action_type>set_attribute_value</action_type>
                  <asset>[[output://create_metadata_field_related_asset_5093479889.assetid]]</asset>
                  <attribute>editable</attribute>
                  <value><![CDATA[1]]></value>
              </action>
              <action>
                  <action_id>set_metadata_field_related_asset_5093479889_editable</action_id>
                  <action_type>set_attribute_value</action_type>
                  <asset>[[output://create_metadata_field_related_asset_5093479889.assetid]]</asset>
                  <attribute>editable</attribute>
                  <value><![CDATA[1]]></value>
              </action>
              <action>
                  <action_id>set_metadata_field_related_asset_5093479889_required</action_id>
                  <action_type>set_attribute_value</action_type>
                  <asset>[[output://create_metadata_field_related_asset_5093479889.assetid]]</asset>
                  <attribute>required</attribute>
                  <value><![CDATA[0]]></value>
              </action>
              <action>
                  <action_id>set_permission_5093479889_read_5</action_id>
                  <action_type>set_permission</action_type>
                  <asset>[[output://create_metadata_field_related_asset_5093479889.assetid]]</asset>
                  <permission>1</permission>
                  <granted>1</granted>
                  <userid>[[system://public_user]]</userid>
              </action>
              
              <action>
                  <action_id>create_metadata_field_select_1292704433</action_id>
                  <action_type>create_asset</action_type>
                  <type_code>metadata_field_select</type_code>
                  <link_type>2</link_type>
                  <parentid>[[output://create_Metadata_Section_3563465437.assetid]]</parentid>
                  <value></value>
                  <is_dependant>1</is_dependant>
                  <is_exclusive>0</is_exclusive>
              </action> 
              <action>
                  <action_id>set_metadata_field_select_1292704433_name</action_id>
                  <action_type>set_attribute_value</action_type>
                  <asset>[[output://create_metadata_field_select_1292704433.assetid]]</asset>
                  <attribute>name</attribute>
                  <value><![CDATA[hero_image_responsive_treatment]]></value>
              </action>
              <action>
                  <action_id>set_metadata_field_select_1292704433_friendly_name</action_id>
                  <action_type>set_attribute_value</action_type>
                  <asset>[[output://create_metadata_field_select_1292704433.assetid]]</asset>
                  <attribute>friendly_name</attribute>
                  <value><![CDATA[Responsive treatment]]></value>
              </action>
              <action>
                  <action_id>set_metadata_field_select_1292704433_default</action_id>
                  <action_type>set_attribute_value</action_type>
                  <asset>[[output://create_metadata_field_select_1292704433.assetid]]</asset>
                  <attribute>default</attribute>
                  <value><![CDATA[crop]]></value>
              </action>
              <action>
                  <action_id>set_metadata_field_select_1292704433_description</action_id>
                  <action_type>set_attribute_value</action_type>
                  <asset>[[output://create_metadata_field_select_1292704433.assetid]]</asset>
                  <attribute>description</attribute>
                  <value><![CDATA[]]></value>
              </action>
              <action>
                  <action_id>set_metadata_field_select_1292704433_editable</action_id>
                  <action_type>set_attribute_value</action_type>
                  <asset>[[output://create_metadata_field_select_1292704433.assetid]]</asset>
                  <attribute>editable</attribute>
                  <value><![CDATA[1]]></value>
              </action>
              <action>
                  <action_id>set_metadata_field_select_1292704433_editable</action_id>
                  <action_type>set_attribute_value</action_type>
                  <asset>[[output://create_metadata_field_select_1292704433.assetid]]</asset>
                  <attribute>editable</attribute>
                  <value><![CDATA[1]]></value>
              </action>
              <action>
                  <action_id>set_metadata_field_select_1292704433_required</action_id>
                  <action_type>set_attribute_value</action_type>
                  <asset>[[output://create_metadata_field_select_1292704433.assetid]]</asset>
                  <attribute>required</attribute>
                  <value><![CDATA[0]]></value>
              </action>
              <action>
                  <action_id>set_permission_1292704433_read_5</action_id>
                  <action_type>set_permission</action_type>
                  <asset>[[output://create_metadata_field_select_1292704433.assetid]]</asset>
                  <permission>1</permission>
                  <granted>1</granted>
                  <userid>[[system://public_user]]</userid>
              </action>
              
                  <action>
                      <action_id>set_metadata_field_select_1292704433_select_options</action_id>
                      <action_type>set_attribute_value</action_type>
                      <asset>[[output://create_metadata_field_select_1292704433.assetid]]</asset>
                      <attribute>select_options</attribute>
                      <value><![CDATA[array ('crop' => 'Crop','scale' => 'Scale',);]]></value>
                  </action>
                  <action>
                      <action_id>set_{f.type}_1292704433_edit_params</action_id>
                      <action_type>set_attribute_value</action_type>
                      <asset>[[output://create_metadata_field_select_1292704433.assetid]]</asset>
                      <attribute>edit_params</attribute>
                      <value><![CDATA[array (
                      'style' => 'list',
                      'type' => 'table',
                      'height' => '',
                      'columns' => '1',
                      'empty_text' => '',
                      'extras' => '',
                      );]]></value>
                  </action>  
                  
              <action>
                  <action_id>create_metadata_field_select_1266257181</action_id>
                  <action_type>create_asset</action_type>
                  <type_code>metadata_field_select</type_code>
                  <link_type>2</link_type>
                  <parentid>[[output://create_Metadata_Section_3563465437.assetid]]</parentid>
                  <value></value>
                  <is_dependant>1</is_dependant>
                  <is_exclusive>0</is_exclusive>
              </action> 
              <action>
                  <action_id>set_metadata_field_select_1266257181_name</action_id>
                  <action_type>set_attribute_value</action_type>
                  <asset>[[output://create_metadata_field_select_1266257181.assetid]]</asset>
                  <attribute>name</attribute>
                  <value><![CDATA[hero_image_padding]]></value>
              </action>
              <action>
                  <action_id>set_metadata_field_select_1266257181_friendly_name</action_id>
                  <action_type>set_attribute_value</action_type>
                  <asset>[[output://create_metadata_field_select_1266257181.assetid]]</asset>
                  <attribute>friendly_name</attribute>
                  <value><![CDATA[Display Padding?]]></value>
              </action>
              <action>
                  <action_id>set_metadata_field_select_1266257181_default</action_id>
                  <action_type>set_attribute_value</action_type>
                  <asset>[[output://create_metadata_field_select_1266257181.assetid]]</asset>
                  <attribute>default</attribute>
                  <value><![CDATA[no]]></value>
              </action>
              <action>
                  <action_id>set_metadata_field_select_1266257181_description</action_id>
                  <action_type>set_attribute_value</action_type>
                  <asset>[[output://create_metadata_field_select_1266257181.assetid]]</asset>
                  <attribute>description</attribute>
                  <value><![CDATA[]]></value>
              </action>
              <action>
                  <action_id>set_metadata_field_select_1266257181_editable</action_id>
                  <action_type>set_attribute_value</action_type>
                  <asset>[[output://create_metadata_field_select_1266257181.assetid]]</asset>
                  <attribute>editable</attribute>
                  <value><![CDATA[1]]></value>
              </action>
              <action>
                  <action_id>set_metadata_field_select_1266257181_editable</action_id>
                  <action_type>set_attribute_value</action_type>
                  <asset>[[output://create_metadata_field_select_1266257181.assetid]]</asset>
                  <attribute>editable</attribute>
                  <value><![CDATA[1]]></value>
              </action>
              <action>
                  <action_id>set_metadata_field_select_1266257181_required</action_id>
                  <action_type>set_attribute_value</action_type>
                  <asset>[[output://create_metadata_field_select_1266257181.assetid]]</asset>
                  <attribute>required</attribute>
                  <value><![CDATA[0]]></value>
              </action>
              <action>
                  <action_id>set_permission_1266257181_read_5</action_id>
                  <action_type>set_permission</action_type>
                  <asset>[[output://create_metadata_field_select_1266257181.assetid]]</asset>
                  <permission>1</permission>
                  <granted>1</granted>
                  <userid>[[system://public_user]]</userid>
              </action>
              
                  <action>
                      <action_id>set_metadata_field_select_1266257181_select_options</action_id>
                      <action_type>set_attribute_value</action_type>
                      <asset>[[output://create_metadata_field_select_1266257181.assetid]]</asset>
                      <attribute>select_options</attribute>
                      <value><![CDATA[array ('no' => 'No','yes' => 'Yes',);]]></value>
                  </action>
                  <action>
                      <action_id>set_{f.type}_1266257181_edit_params</action_id>
                      <action_type>set_attribute_value</action_type>
                      <asset>[[output://create_metadata_field_select_1266257181.assetid]]</asset>
                      <attribute>edit_params</attribute>
                      <value><![CDATA[array (
                      'style' => 'list',
                      'type' => 'table',
                      'height' => '',
                      'columns' => '1',
                      'empty_text' => '',
                      'extras' => '',
                      );]]></value>
                  </action>  
                  
              <action>
                  <action_id>create_metadata_field_select_7113282342</action_id>
                  <action_type>create_asset</action_type>
                  <type_code>metadata_field_select</type_code>
                  <link_type>2</link_type>
                  <parentid>[[output://create_Metadata_Section_3563465437.assetid]]</parentid>
                  <value></value>
                  <is_dependant>1</is_dependant>
                  <is_exclusive>0</is_exclusive>
              </action> 
              <action>
                  <action_id>set_metadata_field_select_7113282342_name</action_id>
                  <action_type>set_attribute_value</action_type>
                  <asset>[[output://create_metadata_field_select_7113282342.assetid]]</asset>
                  <attribute>name</attribute>
                  <value><![CDATA[background_type]]></value>
              </action>
              <action>
                  <action_id>set_metadata_field_select_7113282342_friendly_name</action_id>
                  <action_type>set_attribute_value</action_type>
                  <asset>[[output://create_metadata_field_select_7113282342.assetid]]</asset>
                  <attribute>friendly_name</attribute>
                  <value><![CDATA[Background type]]></value>
              </action>
              <action>
                  <action_id>set_metadata_field_select_7113282342_default</action_id>
                  <action_type>set_attribute_value</action_type>
                  <asset>[[output://create_metadata_field_select_7113282342.assetid]]</asset>
                  <attribute>default</attribute>
                  <value><![CDATA[image]]></value>
              </action>
              <action>
                  <action_id>set_metadata_field_select_7113282342_description</action_id>
                  <action_type>set_attribute_value</action_type>
                  <asset>[[output://create_metadata_field_select_7113282342.assetid]]</asset>
                  <attribute>description</attribute>
                  <value><![CDATA[]]></value>
              </action>
              <action>
                  <action_id>set_metadata_field_select_7113282342_editable</action_id>
                  <action_type>set_attribute_value</action_type>
                  <asset>[[output://create_metadata_field_select_7113282342.assetid]]</asset>
                  <attribute>editable</attribute>
                  <value><![CDATA[1]]></value>
              </action>
              <action>
                  <action_id>set_metadata_field_select_7113282342_editable</action_id>
                  <action_type>set_attribute_value</action_type>
                  <asset>[[output://create_metadata_field_select_7113282342.assetid]]</asset>
                  <attribute>editable</attribute>
                  <value><![CDATA[1]]></value>
              </action>
              <action>
                  <action_id>set_metadata_field_select_7113282342_required</action_id>
                  <action_type>set_attribute_value</action_type>
                  <asset>[[output://create_metadata_field_select_7113282342.assetid]]</asset>
                  <attribute>required</attribute>
                  <value><![CDATA[0]]></value>
              </action>
              <action>
                  <action_id>set_permission_7113282342_read_5</action_id>
                  <action_type>set_permission</action_type>
                  <asset>[[output://create_metadata_field_select_7113282342.assetid]]</asset>
                  <permission>1</permission>
                  <granted>1</granted>
                  <userid>[[system://public_user]]</userid>
              </action>
              
                  <action>
                      <action_id>set_metadata_field_select_7113282342_select_options</action_id>
                      <action_type>set_attribute_value</action_type>
                      <asset>[[output://create_metadata_field_select_7113282342.assetid]]</asset>
                      <attribute>select_options</attribute>
                      <value><![CDATA[array ('colour' => 'Colour','texture' => 'Texture','image' => 'Background Image',);]]></value>
                  </action>
                  <action>
                      <action_id>set_{f.type}_7113282342_edit_params</action_id>
                      <action_type>set_attribute_value</action_type>
                      <asset>[[output://create_metadata_field_select_7113282342.assetid]]</asset>
                      <attribute>edit_params</attribute>
                      <value><![CDATA[array (
                      'style' => 'list',
                      'type' => 'table',
                      'height' => '',
                      'columns' => '1',
                      'empty_text' => '',
                      'extras' => '',
                      );]]></value>
                  </action>  
                  
              <action>
                  <action_id>create_metadata_field_select_6773393429</action_id>
                  <action_type>create_asset</action_type>
                  <type_code>metadata_field_select</type_code>
                  <link_type>2</link_type>
                  <parentid>[[output://create_Metadata_Section_3563465437.assetid]]</parentid>
                  <value></value>
                  <is_dependant>1</is_dependant>
                  <is_exclusive>0</is_exclusive>
              </action> 
              <action>
                  <action_id>set_metadata_field_select_6773393429_name</action_id>
                  <action_type>set_attribute_value</action_type>
                  <asset>[[output://create_metadata_field_select_6773393429.assetid]]</asset>
                  <attribute>name</attribute>
                  <value><![CDATA[background_colour]]></value>
              </action>
              <action>
                  <action_id>set_metadata_field_select_6773393429_friendly_name</action_id>
                  <action_type>set_attribute_value</action_type>
                  <asset>[[output://create_metadata_field_select_6773393429.assetid]]</asset>
                  <attribute>friendly_name</attribute>
                  <value><![CDATA[Background Colour]]></value>
              </action>
              <action>
                  <action_id>set_metadata_field_select_6773393429_default</action_id>
                  <action_type>set_attribute_value</action_type>
                  <asset>[[output://create_metadata_field_select_6773393429.assetid]]</asset>
                  <attribute>default</attribute>
                  <value><![CDATA[dark]]></value>
              </action>
              <action>
                  <action_id>set_metadata_field_select_6773393429_description</action_id>
                  <action_type>set_attribute_value</action_type>
                  <asset>[[output://create_metadata_field_select_6773393429.assetid]]</asset>
                  <attribute>description</attribute>
                  <value><![CDATA[]]></value>
              </action>
              <action>
                  <action_id>set_metadata_field_select_6773393429_editable</action_id>
                  <action_type>set_attribute_value</action_type>
                  <asset>[[output://create_metadata_field_select_6773393429.assetid]]</asset>
                  <attribute>editable</attribute>
                  <value><![CDATA[1]]></value>
              </action>
              <action>
                  <action_id>set_metadata_field_select_6773393429_editable</action_id>
                  <action_type>set_attribute_value</action_type>
                  <asset>[[output://create_metadata_field_select_6773393429.assetid]]</asset>
                  <attribute>editable</attribute>
                  <value><![CDATA[1]]></value>
              </action>
              <action>
                  <action_id>set_metadata_field_select_6773393429_required</action_id>
                  <action_type>set_attribute_value</action_type>
                  <asset>[[output://create_metadata_field_select_6773393429.assetid]]</asset>
                  <attribute>required</attribute>
                  <value><![CDATA[0]]></value>
              </action>
              <action>
                  <action_id>set_permission_6773393429_read_5</action_id>
                  <action_type>set_permission</action_type>
                  <asset>[[output://create_metadata_field_select_6773393429.assetid]]</asset>
                  <permission>1</permission>
                  <granted>1</granted>
                  <userid>[[system://public_user]]</userid>
              </action>
              
                  <action>
                      <action_id>set_metadata_field_select_6773393429_select_options</action_id>
                      <action_type>set_attribute_value</action_type>
                      <asset>[[output://create_metadata_field_select_6773393429.assetid]]</asset>
                      <attribute>select_options</attribute>
                      <value><![CDATA[array ('' => 'White','light' => 'Light','alternate' => 'Alternate','dark' => 'Dark','dark-alternate' => 'Dark Alternate',);]]></value>
                  </action>
                  <action>
                      <action_id>set_{f.type}_6773393429_edit_params</action_id>
                      <action_type>set_attribute_value</action_type>
                      <asset>[[output://create_metadata_field_select_6773393429.assetid]]</asset>
                      <attribute>edit_params</attribute>
                      <value><![CDATA[array (
                      'style' => 'list',
                      'type' => 'table',
                      'height' => '',
                      'columns' => '1',
                      'empty_text' => '',
                      'extras' => '',
                      );]]></value>
                  </action>  
                  
              <action>
                  <action_id>create_metadata_field_related_asset_9249212703</action_id>
                  <action_type>create_asset</action_type>
                  <type_code>metadata_field_related_asset</type_code>
                  <link_type>2</link_type>
                  <parentid>[[output://create_Metadata_Section_3563465437.assetid]]</parentid>
                  <value></value>
                  <is_dependant>1</is_dependant>
                  <is_exclusive>0</is_exclusive>
              </action> 
              <action>
                  <action_id>set_metadata_field_related_asset_9249212703_name</action_id>
                  <action_type>set_attribute_value</action_type>
                  <asset>[[output://create_metadata_field_related_asset_9249212703.assetid]]</asset>
                  <attribute>name</attribute>
                  <value><![CDATA[background_image_sm]]></value>
              </action>
              <action>
                  <action_id>set_metadata_field_related_asset_9249212703_friendly_name</action_id>
                  <action_type>set_attribute_value</action_type>
                  <asset>[[output://create_metadata_field_related_asset_9249212703.assetid]]</asset>
                  <attribute>friendly_name</attribute>
                  <value><![CDATA[Background Image - Mobile]]></value>
              </action>
              <action>
                  <action_id>set_metadata_field_related_asset_9249212703_default</action_id>
                  <action_type>set_attribute_value</action_type>
                  <asset>[[output://create_metadata_field_related_asset_9249212703.assetid]]</asset>
                  <attribute>default</attribute>
                  <value><![CDATA[/mysource_files/banner-bg.png]]></value>
              </action>
              <action>
                  <action_id>set_metadata_field_related_asset_9249212703_description</action_id>
                  <action_type>set_attribute_value</action_type>
                  <asset>[[output://create_metadata_field_related_asset_9249212703.assetid]]</asset>
                  <attribute>description</attribute>
                  <value><![CDATA[]]></value>
              </action>
              <action>
                  <action_id>set_metadata_field_related_asset_9249212703_editable</action_id>
                  <action_type>set_attribute_value</action_type>
                  <asset>[[output://create_metadata_field_related_asset_9249212703.assetid]]</asset>
                  <attribute>editable</attribute>
                  <value><![CDATA[1]]></value>
              </action>
              <action>
                  <action_id>set_metadata_field_related_asset_9249212703_editable</action_id>
                  <action_type>set_attribute_value</action_type>
                  <asset>[[output://create_metadata_field_related_asset_9249212703.assetid]]</asset>
                  <attribute>editable</attribute>
                  <value><![CDATA[1]]></value>
              </action>
              <action>
                  <action_id>set_metadata_field_related_asset_9249212703_required</action_id>
                  <action_type>set_attribute_value</action_type>
                  <asset>[[output://create_metadata_field_related_asset_9249212703.assetid]]</asset>
                  <attribute>required</attribute>
                  <value><![CDATA[0]]></value>
              </action>
              <action>
                  <action_id>set_permission_9249212703_read_5</action_id>
                  <action_type>set_permission</action_type>
                  <asset>[[output://create_metadata_field_related_asset_9249212703.assetid]]</asset>
                  <permission>1</permission>
                  <granted>1</granted>
                  <userid>[[system://public_user]]</userid>
              </action>
              
              <action>
                  <action_id>create_metadata_field_related_asset_6501365787</action_id>
                  <action_type>create_asset</action_type>
                  <type_code>metadata_field_related_asset</type_code>
                  <link_type>2</link_type>
                  <parentid>[[output://create_Metadata_Section_3563465437.assetid]]</parentid>
                  <value></value>
                  <is_dependant>1</is_dependant>
                  <is_exclusive>0</is_exclusive>
              </action> 
              <action>
                  <action_id>set_metadata_field_related_asset_6501365787_name</action_id>
                  <action_type>set_attribute_value</action_type>
                  <asset>[[output://create_metadata_field_related_asset_6501365787.assetid]]</asset>
                  <attribute>name</attribute>
                  <value><![CDATA[background_image_lg]]></value>
              </action>
              <action>
                  <action_id>set_metadata_field_related_asset_6501365787_friendly_name</action_id>
                  <action_type>set_attribute_value</action_type>
                  <asset>[[output://create_metadata_field_related_asset_6501365787.assetid]]</asset>
                  <attribute>friendly_name</attribute>
                  <value><![CDATA[Background Image - Desktop and Tablet]]></value>
              </action>
              <action>
                  <action_id>set_metadata_field_related_asset_6501365787_default</action_id>
                  <action_type>set_attribute_value</action_type>
                  <asset>[[output://create_metadata_field_related_asset_6501365787.assetid]]</asset>
                  <attribute>default</attribute>
                  <value><![CDATA[/mysource_files/banner-bg.png]]></value>
              </action>
              <action>
                  <action_id>set_metadata_field_related_asset_6501365787_description</action_id>
                  <action_type>set_attribute_value</action_type>
                  <asset>[[output://create_metadata_field_related_asset_6501365787.assetid]]</asset>
                  <attribute>description</attribute>
                  <value><![CDATA[]]></value>
              </action>
              <action>
                  <action_id>set_metadata_field_related_asset_6501365787_editable</action_id>
                  <action_type>set_attribute_value</action_type>
                  <asset>[[output://create_metadata_field_related_asset_6501365787.assetid]]</asset>
                  <attribute>editable</attribute>
                  <value><![CDATA[1]]></value>
              </action>
              <action>
                  <action_id>set_metadata_field_related_asset_6501365787_editable</action_id>
                  <action_type>set_attribute_value</action_type>
                  <asset>[[output://create_metadata_field_related_asset_6501365787.assetid]]</asset>
                  <attribute>editable</attribute>
                  <value><![CDATA[1]]></value>
              </action>
              <action>
                  <action_id>set_metadata_field_related_asset_6501365787_required</action_id>
                  <action_type>set_attribute_value</action_type>
                  <asset>[[output://create_metadata_field_related_asset_6501365787.assetid]]</asset>
                  <attribute>required</attribute>
                  <value><![CDATA[0]]></value>
              </action>
              <action>
                  <action_id>set_permission_6501365787_read_5</action_id>
                  <action_type>set_permission</action_type>
                  <asset>[[output://create_metadata_field_related_asset_6501365787.assetid]]</asset>
                  <permission>1</permission>
                  <granted>1</granted>
                  <userid>[[system://public_user]]</userid>
              </action>
              
              <action>
                  <action_id>create_metadata_field_select_2068222157</action_id>
                  <action_type>create_asset</action_type>
                  <type_code>metadata_field_select</type_code>
                  <link_type>2</link_type>
                  <parentid>[[output://create_Metadata_Section_3563465437.assetid]]</parentid>
                  <value></value>
                  <is_dependant>1</is_dependant>
                  <is_exclusive>0</is_exclusive>
              </action> 
              <action>
                  <action_id>set_metadata_field_select_2068222157_name</action_id>
                  <action_type>set_attribute_value</action_type>
                  <asset>[[output://create_metadata_field_select_2068222157.assetid]]</asset>
                  <attribute>name</attribute>
                  <value><![CDATA[background_image_alignment]]></value>
              </action>
              <action>
                  <action_id>set_metadata_field_select_2068222157_friendly_name</action_id>
                  <action_type>set_attribute_value</action_type>
                  <asset>[[output://create_metadata_field_select_2068222157.assetid]]</asset>
                  <attribute>friendly_name</attribute>
                  <value><![CDATA[Background alignment]]></value>
              </action>
              <action>
                  <action_id>set_metadata_field_select_2068222157_default</action_id>
                  <action_type>set_attribute_value</action_type>
                  <asset>[[output://create_metadata_field_select_2068222157.assetid]]</asset>
                  <attribute>default</attribute>
                  <value><![CDATA[center]]></value>
              </action>
              <action>
                  <action_id>set_metadata_field_select_2068222157_description</action_id>
                  <action_type>set_attribute_value</action_type>
                  <asset>[[output://create_metadata_field_select_2068222157.assetid]]</asset>
                  <attribute>description</attribute>
                  <value><![CDATA[]]></value>
              </action>
              <action>
                  <action_id>set_metadata_field_select_2068222157_editable</action_id>
                  <action_type>set_attribute_value</action_type>
                  <asset>[[output://create_metadata_field_select_2068222157.assetid]]</asset>
                  <attribute>editable</attribute>
                  <value><![CDATA[1]]></value>
              </action>
              <action>
                  <action_id>set_metadata_field_select_2068222157_editable</action_id>
                  <action_type>set_attribute_value</action_type>
                  <asset>[[output://create_metadata_field_select_2068222157.assetid]]</asset>
                  <attribute>editable</attribute>
                  <value><![CDATA[1]]></value>
              </action>
              <action>
                  <action_id>set_metadata_field_select_2068222157_required</action_id>
                  <action_type>set_attribute_value</action_type>
                  <asset>[[output://create_metadata_field_select_2068222157.assetid]]</asset>
                  <attribute>required</attribute>
                  <value><![CDATA[0]]></value>
              </action>
              <action>
                  <action_id>set_permission_2068222157_read_5</action_id>
                  <action_type>set_permission</action_type>
                  <asset>[[output://create_metadata_field_select_2068222157.assetid]]</asset>
                  <permission>1</permission>
                  <granted>1</granted>
                  <userid>[[system://public_user]]</userid>
              </action>
              
                  <action>
                      <action_id>set_metadata_field_select_2068222157_select_options</action_id>
                      <action_type>set_attribute_value</action_type>
                      <asset>[[output://create_metadata_field_select_2068222157.assetid]]</asset>
                      <attribute>select_options</attribute>
                      <value><![CDATA[array ('left' => 'Left','right' => 'Right','center' => 'Center',);]]></value>
                  </action>
                  <action>
                      <action_id>set_{f.type}_2068222157_edit_params</action_id>
                      <action_type>set_attribute_value</action_type>
                      <asset>[[output://create_metadata_field_select_2068222157.assetid]]</asset>
                      <attribute>edit_params</attribute>
                      <value><![CDATA[array (
                      'style' => 'list',
                      'type' => 'table',
                      'height' => '',
                      'columns' => '1',
                      'empty_text' => '',
                      'extras' => '',
                      );]]></value>
                  </action>  
                  
              <action>
                  <action_id>create_metadata_field_text_9844034233</action_id>
                  <action_type>create_asset</action_type>
                  <type_code>metadata_field_text</type_code>
                  <link_type>2</link_type>
                  <parentid>[[output://create_Metadata_Section_3563465437.assetid]]</parentid>
                  <value></value>
                  <is_dependant>1</is_dependant>
                  <is_exclusive>0</is_exclusive>
              </action> 
              <action>
                  <action_id>set_metadata_field_text_9844034233_name</action_id>
                  <action_type>set_attribute_value</action_type>
                  <asset>[[output://create_metadata_field_text_9844034233.assetid]]</asset>
                  <attribute>name</attribute>
                  <value><![CDATA[cta_button_primary_text]]></value>
              </action>
              <action>
                  <action_id>set_metadata_field_text_9844034233_friendly_name</action_id>
                  <action_type>set_attribute_value</action_type>
                  <asset>[[output://create_metadata_field_text_9844034233.assetid]]</asset>
                  <attribute>friendly_name</attribute>
                  <value><![CDATA[Primary Button Text]]></value>
              </action>
              <action>
                  <action_id>set_metadata_field_text_9844034233_default</action_id>
                  <action_type>set_attribute_value</action_type>
                  <asset>[[output://create_metadata_field_text_9844034233.assetid]]</asset>
                  <attribute>default</attribute>
                  <value><![CDATA[Primary Button]]></value>
              </action>
              <action>
                  <action_id>set_metadata_field_text_9844034233_description</action_id>
                  <action_type>set_attribute_value</action_type>
                  <asset>[[output://create_metadata_field_text_9844034233.assetid]]</asset>
                  <attribute>description</attribute>
                  <value><![CDATA[]]></value>
              </action>
              <action>
                  <action_id>set_metadata_field_text_9844034233_editable</action_id>
                  <action_type>set_attribute_value</action_type>
                  <asset>[[output://create_metadata_field_text_9844034233.assetid]]</asset>
                  <attribute>editable</attribute>
                  <value><![CDATA[1]]></value>
              </action>
              <action>
                  <action_id>set_metadata_field_text_9844034233_editable</action_id>
                  <action_type>set_attribute_value</action_type>
                  <asset>[[output://create_metadata_field_text_9844034233.assetid]]</asset>
                  <attribute>editable</attribute>
                  <value><![CDATA[1]]></value>
              </action>
              <action>
                  <action_id>set_metadata_field_text_9844034233_required</action_id>
                  <action_type>set_attribute_value</action_type>
                  <asset>[[output://create_metadata_field_text_9844034233.assetid]]</asset>
                  <attribute>required</attribute>
                  <value><![CDATA[0]]></value>
              </action>
              <action>
                  <action_id>set_permission_9844034233_read_5</action_id>
                  <action_type>set_permission</action_type>
                  <asset>[[output://create_metadata_field_text_9844034233.assetid]]</asset>
                  <permission>1</permission>
                  <granted>1</granted>
                  <userid>[[system://public_user]]</userid>
              </action>
              
              <action>
                  <action_id>create_metadata_field_related_asset_3681758151</action_id>
                  <action_type>create_asset</action_type>
                  <type_code>metadata_field_related_asset</type_code>
                  <link_type>2</link_type>
                  <parentid>[[output://create_Metadata_Section_3563465437.assetid]]</parentid>
                  <value></value>
                  <is_dependant>1</is_dependant>
                  <is_exclusive>0</is_exclusive>
              </action> 
              <action>
                  <action_id>set_metadata_field_related_asset_3681758151_name</action_id>
                  <action_type>set_attribute_value</action_type>
                  <asset>[[output://create_metadata_field_related_asset_3681758151.assetid]]</asset>
                  <attribute>name</attribute>
                  <value><![CDATA[cta_button_primary_link]]></value>
              </action>
              <action>
                  <action_id>set_metadata_field_related_asset_3681758151_friendly_name</action_id>
                  <action_type>set_attribute_value</action_type>
                  <asset>[[output://create_metadata_field_related_asset_3681758151.assetid]]</asset>
                  <attribute>friendly_name</attribute>
                  <value><![CDATA[Primary Button Link]]></value>
              </action>
              <action>
                  <action_id>set_metadata_field_related_asset_3681758151_default</action_id>
                  <action_type>set_attribute_value</action_type>
                  <asset>[[output://create_metadata_field_related_asset_3681758151.assetid]]</asset>
                  <attribute>default</attribute>
                  <value><![CDATA[#]]></value>
              </action>
              <action>
                  <action_id>set_metadata_field_related_asset_3681758151_description</action_id>
                  <action_type>set_attribute_value</action_type>
                  <asset>[[output://create_metadata_field_related_asset_3681758151.assetid]]</asset>
                  <attribute>description</attribute>
                  <value><![CDATA[]]></value>
              </action>
              <action>
                  <action_id>set_metadata_field_related_asset_3681758151_editable</action_id>
                  <action_type>set_attribute_value</action_type>
                  <asset>[[output://create_metadata_field_related_asset_3681758151.assetid]]</asset>
                  <attribute>editable</attribute>
                  <value><![CDATA[1]]></value>
              </action>
              <action>
                  <action_id>set_metadata_field_related_asset_3681758151_editable</action_id>
                  <action_type>set_attribute_value</action_type>
                  <asset>[[output://create_metadata_field_related_asset_3681758151.assetid]]</asset>
                  <attribute>editable</attribute>
                  <value><![CDATA[1]]></value>
              </action>
              <action>
                  <action_id>set_metadata_field_related_asset_3681758151_required</action_id>
                  <action_type>set_attribute_value</action_type>
                  <asset>[[output://create_metadata_field_related_asset_3681758151.assetid]]</asset>
                  <attribute>required</attribute>
                  <value><![CDATA[0]]></value>
              </action>
              <action>
                  <action_id>set_permission_3681758151_read_5</action_id>
                  <action_type>set_permission</action_type>
                  <asset>[[output://create_metadata_field_related_asset_3681758151.assetid]]</asset>
                  <permission>1</permission>
                  <granted>1</granted>
                  <userid>[[system://public_user]]</userid>
              </action>
              
              <action>
                  <action_id>create_metadata_field_text_5529337151</action_id>
                  <action_type>create_asset</action_type>
                  <type_code>metadata_field_text</type_code>
                  <link_type>2</link_type>
                  <parentid>[[output://create_Metadata_Section_3563465437.assetid]]</parentid>
                  <value></value>
                  <is_dependant>1</is_dependant>
                  <is_exclusive>0</is_exclusive>
              </action> 
              <action>
                  <action_id>set_metadata_field_text_5529337151_name</action_id>
                  <action_type>set_attribute_value</action_type>
                  <asset>[[output://create_metadata_field_text_5529337151.assetid]]</asset>
                  <attribute>name</attribute>
                  <value><![CDATA[cta_button_secondary_text]]></value>
              </action>
              <action>
                  <action_id>set_metadata_field_text_5529337151_friendly_name</action_id>
                  <action_type>set_attribute_value</action_type>
                  <asset>[[output://create_metadata_field_text_5529337151.assetid]]</asset>
                  <attribute>friendly_name</attribute>
                  <value><![CDATA[Secondary Button Text]]></value>
              </action>
              <action>
                  <action_id>set_metadata_field_text_5529337151_default</action_id>
                  <action_type>set_attribute_value</action_type>
                  <asset>[[output://create_metadata_field_text_5529337151.assetid]]</asset>
                  <attribute>default</attribute>
                  <value><![CDATA[Secondary Button]]></value>
              </action>
              <action>
                  <action_id>set_metadata_field_text_5529337151_description</action_id>
                  <action_type>set_attribute_value</action_type>
                  <asset>[[output://create_metadata_field_text_5529337151.assetid]]</asset>
                  <attribute>description</attribute>
                  <value><![CDATA[]]></value>
              </action>
              <action>
                  <action_id>set_metadata_field_text_5529337151_editable</action_id>
                  <action_type>set_attribute_value</action_type>
                  <asset>[[output://create_metadata_field_text_5529337151.assetid]]</asset>
                  <attribute>editable</attribute>
                  <value><![CDATA[1]]></value>
              </action>
              <action>
                  <action_id>set_metadata_field_text_5529337151_editable</action_id>
                  <action_type>set_attribute_value</action_type>
                  <asset>[[output://create_metadata_field_text_5529337151.assetid]]</asset>
                  <attribute>editable</attribute>
                  <value><![CDATA[1]]></value>
              </action>
              <action>
                  <action_id>set_metadata_field_text_5529337151_required</action_id>
                  <action_type>set_attribute_value</action_type>
                  <asset>[[output://create_metadata_field_text_5529337151.assetid]]</asset>
                  <attribute>required</attribute>
                  <value><![CDATA[0]]></value>
              </action>
              <action>
                  <action_id>set_permission_5529337151_read_5</action_id>
                  <action_type>set_permission</action_type>
                  <asset>[[output://create_metadata_field_text_5529337151.assetid]]</asset>
                  <permission>1</permission>
                  <granted>1</granted>
                  <userid>[[system://public_user]]</userid>
              </action>
              
              <action>
                  <action_id>create_metadata_field_related_asset_5492798533</action_id>
                  <action_type>create_asset</action_type>
                  <type_code>metadata_field_related_asset</type_code>
                  <link_type>2</link_type>
                  <parentid>[[output://create_Metadata_Section_3563465437.assetid]]</parentid>
                  <value></value>
                  <is_dependant>1</is_dependant>
                  <is_exclusive>0</is_exclusive>
              </action> 
              <action>
                  <action_id>set_metadata_field_related_asset_5492798533_name</action_id>
                  <action_type>set_attribute_value</action_type>
                  <asset>[[output://create_metadata_field_related_asset_5492798533.assetid]]</asset>
                  <attribute>name</attribute>
                  <value><![CDATA[cta_button_secondary_link]]></value>
              </action>
              <action>
                  <action_id>set_metadata_field_related_asset_5492798533_friendly_name</action_id>
                  <action_type>set_attribute_value</action_type>
                  <asset>[[output://create_metadata_field_related_asset_5492798533.assetid]]</asset>
                  <attribute>friendly_name</attribute>
                  <value><![CDATA[Secondary Button Link]]></value>
              </action>
              <action>
                  <action_id>set_metadata_field_related_asset_5492798533_default</action_id>
                  <action_type>set_attribute_value</action_type>
                  <asset>[[output://create_metadata_field_related_asset_5492798533.assetid]]</asset>
                  <attribute>default</attribute>
                  <value><![CDATA[#]]></value>
              </action>
              <action>
                  <action_id>set_metadata_field_related_asset_5492798533_description</action_id>
                  <action_type>set_attribute_value</action_type>
                  <asset>[[output://create_metadata_field_related_asset_5492798533.assetid]]</asset>
                  <attribute>description</attribute>
                  <value><![CDATA[]]></value>
              </action>
              <action>
                  <action_id>set_metadata_field_related_asset_5492798533_editable</action_id>
                  <action_type>set_attribute_value</action_type>
                  <asset>[[output://create_metadata_field_related_asset_5492798533.assetid]]</asset>
                  <attribute>editable</attribute>
                  <value><![CDATA[1]]></value>
              </action>
              <action>
                  <action_id>set_metadata_field_related_asset_5492798533_editable</action_id>
                  <action_type>set_attribute_value</action_type>
                  <asset>[[output://create_metadata_field_related_asset_5492798533.assetid]]</asset>
                  <attribute>editable</attribute>
                  <value><![CDATA[1]]></value>
              </action>
              <action>
                  <action_id>set_metadata_field_related_asset_5492798533_required</action_id>
                  <action_type>set_attribute_value</action_type>
                  <asset>[[output://create_metadata_field_related_asset_5492798533.assetid]]</asset>
                  <attribute>required</attribute>
                  <value><![CDATA[0]]></value>
              </action>
              <action>
                  <action_id>set_permission_5492798533_read_5</action_id>
                  <action_type>set_permission</action_type>
                  <asset>[[output://create_metadata_field_related_asset_5492798533.assetid]]</asset>
                  <permission>1</permission>
                  <granted>1</granted>
                  <userid>[[system://public_user]]</userid>
              </action>
              
              <action>
                  <action_id>create_metadata_field_text_5469983281</action_id>
                  <action_type>create_asset</action_type>
                  <type_code>metadata_field_text</type_code>
                  <link_type>2</link_type>
                  <parentid>[[output://create_Metadata_Section_3563465437.assetid]]</parentid>
                  <value></value>
                  <is_dependant>1</is_dependant>
                  <is_exclusive>0</is_exclusive>
              </action> 
              <action>
                  <action_id>set_metadata_field_text_5469983281_name</action_id>
                  <action_type>set_attribute_value</action_type>
                  <asset>[[output://create_metadata_field_text_5469983281.assetid]]</asset>
                  <attribute>name</attribute>
                  <value><![CDATA[id_field]]></value>
              </action>
              <action>
                  <action_id>set_metadata_field_text_5469983281_friendly_name</action_id>
                  <action_type>set_attribute_value</action_type>
                  <asset>[[output://create_metadata_field_text_5469983281.assetid]]</asset>
                  <attribute>friendly_name</attribute>
                  <value><![CDATA[Id field]]></value>
              </action>
              <action>
                  <action_id>set_metadata_field_text_5469983281_default</action_id>
                  <action_type>set_attribute_value</action_type>
                  <asset>[[output://create_metadata_field_text_5469983281.assetid]]</asset>
                  <attribute>default</attribute>
                  <value><![CDATA[]]></value>
              </action>
              <action>
                  <action_id>set_metadata_field_text_5469983281_description</action_id>
                  <action_type>set_attribute_value</action_type>
                  <asset>[[output://create_metadata_field_text_5469983281.assetid]]</asset>
                  <attribute>description</attribute>
                  <value><![CDATA[]]></value>
              </action>
              <action>
                  <action_id>set_metadata_field_text_5469983281_editable</action_id>
                  <action_type>set_attribute_value</action_type>
                  <asset>[[output://create_metadata_field_text_5469983281.assetid]]</asset>
                  <attribute>editable</attribute>
                  <value><![CDATA[1]]></value>
              </action>
              <action>
                  <action_id>set_metadata_field_text_5469983281_editable</action_id>
                  <action_type>set_attribute_value</action_type>
                  <asset>[[output://create_metadata_field_text_5469983281.assetid]]</asset>
                  <attribute>editable</attribute>
                  <value><![CDATA[1]]></value>
              </action>
              <action>
                  <action_id>set_metadata_field_text_5469983281_required</action_id>
                  <action_type>set_attribute_value</action_type>
                  <asset>[[output://create_metadata_field_text_5469983281.assetid]]</asset>
                  <attribute>required</attribute>
                  <value><![CDATA[0]]></value>
              </action>
              <action>
                  <action_id>set_permission_5469983281_read_5</action_id>
                  <action_type>set_permission</action_type>
                  <asset>[[output://create_metadata_field_text_5469983281.assetid]]</asset>
                  <permission>1</permission>
                  <granted>1</granted>
                  <userid>[[system://public_user]]</userid>
              </action>
              </actions>